Workbook

Sheet Cover
B2: BOSTON UNIVERSITY
B3: AD713 Derivative Securities and Markets
B6: S&P 500 INDEX SHORT STRANGLE
B7: Systematic Volatility Monetization with Delta-Based Hedging
B9: Team Project 2 | Options Portfolio Management
B11: Analyst: Tejasvi Gupta
B12: Instructor: Prof. Christopher Athaide
B13: Trading Period: March 26 - April 24, 2026
B14: Option Expiry: May 16, 2026 (SPX index options)
B15: Marking Convention: End-of-day prices; instructor-posted implied volatilities
B18: WORKBOOK CONTENTS
B20: 1. Executive Summary - Strategy thesis, performance scorecard, and risk retrospective
... B28: Final Portfolio P&L: +$135.31 | ~29.8% of premium collected | 4 executions over 21 trading days

Sheet Executive Summary
B2: EXECUTIVE SUMMARY
B3: S&P 500 Short Strangle | Mar 26 - Apr 24, 2026
B5: PERFORMANCE SCORECARD
B7: Net premium collected | C7: ='Strategy & Risk'!C16 -> 453.7 | E7: Executions (incl. roll legs) | F7: 4
B8: Final portfolio P&L | C8: ='Daily P&L Monitor'!I26 -> 135.31 | E8: Trading days monitored | F8: =COUNT('Daily P&L Monitor'!B6:B26) -> 21
B9: Return on premium collected | C9: =C8/C7 -> 0.29823672 | E9: S&P 500: initiation close | F9: ='Daily P&L Monitor'!C6 -> 6368.85
B10: Peak P&L (Apr 7) | C10: =MAX('Daily P&L Monitor'!I6:I26) -> 154.6 | E10: S&P 500: project-end close (ATH) | F10: ='Daily P&L Monitor'!C26 -> 7165.08
B11: Post-shock trough P&L (Apr 9) | C11: =MIN('Daily P&L Monitor'!I14:I26) -> 84.47 | E11: Index move over period | F11: =F10/F9-1 -> 0.12501943
B14: STRATEGY THESIS
B15: Initiated a short strangle on the S&P 500 Index (sold 6385 put / sold 6595 call, May 16, 2026 expiry) to monetize elevated implied volatility. With the VIX at 25-30 on Middle East conflict risk, option premiums were rich relative to likely realized volatility, and conflict headlines appeared largely priced in. Thesis: index range-bound (~6365-6615) through expiry. Collected $453.70 in premium to harvest theta on both legs, with a stated policy of hedging when portfolio delta breached a +/-0.20 band.
B20: OUTCOME
B21: The position performed as designed for the first two weeks: the index held within the projected range, both legs decayed, and P&L peaked at +$154.60 on Apr 7. On Apr 8 a ceasefire announcement drove the S&P up ~2.5% (oil -17%, VIX to 21), pushing the short call deep in-the-money. The call had been rolled 6595 to 6625 on Apr 6 (net cost $15.20, executed at the -0.20 delta trigger); the rolled call was closed on Apr 9 at $298.59, crystallizing -$86.29 on the call side. The short put was retained through project end, decaying from $226.20 to $4.60 as the index set successive all-time highs. Final P&L: +$135.31, ~29.8% of premium collected.
B27: RISK RETROSPECTIVE & LESSONS
B28: Two governance findings. (1) Threshold discipline: portfolio delta reached -0.42 on Apr 8, more than 2x the stated +/-0.20 limit, before the closing trade was executed on Apr 9. The one-session delay - waiting to confirm the rally - added an estimated $30-40 to the buyback cost. Rule adopted: when delta exceeds 2x the policy threshold with an identifiable directional catalyst, close immediately rather than wait for confirmation. (2) Structure selection: an undefined-risk short strangle was mismatched to a binary-headline regime. A defined-risk structure (iron condor or credit put spread) would have capped call-side tail risk while preserving most of the theta capture. Execution was disciplined on the Apr 6 roll; the structural choice, not the mechanics, was the primary constraint on performance.

Sheet Strategy & Risk
B2: STRATEGY & RISK FRAMEWORK
B4: MARKET VIEW / OBJECTIVE
B5: Expected the S&P 500 to remain range-bound (~6365-6615) through the May 16 expiry. Elevated implied volatility (VIX 25-30 on the Iran conflict) made option premiums rich relative to likely realized volatility; the geopolitical risk premium appeared fully priced. Objective: monetize the implied-vs-realized volatility spread and time decay (theta) on both legs via a short strangle, with no net directional bet at initiation.
B10: INITIAL POSITIONS - executed Mar 27, 2026 EOD (selected by Mar 26 per project deadline)
B11: Leg | C11: Type | D11: Strike | E11: Buy / Sell | F11: Qty | G11: Premium ($) | H11: IV at Entry | I11: Expiry
B12: 1 | C12: Put | D12: 6385 | E12: Sell | F12: -1 | G12: 226.2 | H12: 0.2515 | I12: May 16, 2026
B13: 2 | C13: Call | D13: 6595 | E13: Sell | F13: -1 | G13: 227.5 | H13: 0.2079 | I13: May 16, 2026
B15: POSITION ECONOMICS (AT INITIATION)
B16: Net premium collected ($) | C16: =G12+G13 -> 453.7 | D16: Sum of both short legs
B17: Lower break-even (index) | C17: =D12-C16 -> 5931.3 | D17: Put strike less net premium
B18: Upper break-even (index) | C18: =D13+C16 -> 7048.7 | D18: Call strike plus net premium
B19: Max profit at expiry ($) | C19: =C16 -> 453.7 | D19: Full premium if 6385 < S < 6595 at expiry
B20: Max loss | C20: Unlimited | D20: Undefined-risk structure on both tails
B23: HEDGE POLICY (STATED EX-ANTE)
B24: 1. Monitor portfolio delta daily against instructor-posted EOD marks and updated implied volatilities.
B25: 2. If |portfolio delta| > 0.20, evaluate and execute an adjustment (roll, partial close, or full close).
B26: 3. If spot approaches either strike within 50 points, evaluate rolling that leg further out-of-the-money.
B27: 4. If a strike is breached, close or roll the breached leg; do not add to losing legs.
B28: 5. Tighten the delta band to +/-0.10 in the final two weeks as gamma rises into expiry.
B30: ADJUSTMENTS EXECUTED
B31: Apr 6: Rolled short call 6595 to 6625 - bought back 6595 at $189.66 (realized +$37.84), sold 6625 at $174.46; net roll cost $15.20. Trigger: spot through strike, delta approaching -0.20 band.
B33: Apr 9: Closed 6625 call at $298.59 to cap directional loss after the Apr 8 ceasefire rally. Net realized call-side P&L across both legs: -$86.29.
B36: PRIMARY RISKS & MITIGANTS
B37: (i) Directional: a sustained move beyond either break-even (5,931.30 / 7,048.70) produces open-ended losses. (ii) Volatility: the position is short vega on both legs, so an implied-volatility spike marks the book down even absent a spot move. (iii) Gamma: negative gamma accelerates delta drift near the strikes, particularly into expiry. Mitigants: daily monitoring, pre-defined delta triggers, and willingness to roll or close breached legs.

Sheet Pricing Model
B2: BLACK-SCHOLES-MERTON PRICING MODEL
B3: European index options with continuous dividend yield | Marks as of Apr 24, 2026 (project end)
B5: MODEL INPUTS & OUTPUTS
B6: Position | C6: Spot (S) | D6: Strike (K) | E6: Impl. Vol | F6: T (yrs) | G6: Risk-free r | H6: Div. yield q | I6: Disc. Factor | J6: d1 | K6: d2 | L6: Call ($) | M6: Put ($) | N6: Call Delta | O6: Put Delta | P6: Gamma | Q6: Vega / 1% | R6: Call Theta/d | S6: Put Theta/d
B7: Short Put 6385 (open) | C7: 7165.08 | D7: 6385 | E7: 0.2515 | F7: 0.060273973 | G7: 0.043 | H7: 0.013 | I7: =EXP(-G7*F7) -> 0.99741157 | J7: =(LN(C7/D7)+((G7-H7)-0.5*E7^2)*F7)/MAX(E7*SQRT(F7),0.0001) -> 1.865243 | K7: =J7-E7*SQRT(F7) -> 1.8034979 | L7: =C7*EXP(-H7*F7)*_xlfn.NORM.S.DIST(J7,TRUE())-D7*I7*_xlfn.NORM.S.DIST(K7,TRUE()) -> 795.59213 | M7: =-C7*EXP(-H7*F7)*_xlfn.NORM.S.DIST(-J7,TRUE())+D7*I7*_xlfn.NORM.S.DIST(-K7,TRUE()) -> 4.5971229 | N7: =EXP(-H7*F7)*_xlfn.NORM.S.DIST(J7,TRUE()) -> 0.96816741 | O7: =-EXP(-H7*F7)*_xlfn.NORM.S.DIST(-J7,TRUE()) -> -0.031049334 | P7: =EXP(-H7*F7)*EXP(-0.5*J7^2)/(SQRT(2*PI())*C7*E7*SQRT(F7)) -> 0.00015822023 | Q7: =C7*EXP(-H7*F7)*SQRT(F7)*EXP(-0.5*J7^2)/SQRT(2*PI())/100 -> 1.2313227 | R7: =(-C7*EXP(-H7*F7)*E7*EXP(-0.5*J7^2)/(2*SQRT(2*PI()*F7))-G7*D7*I7*_xlfn.NORM.S.DIST(K7,TRUE())+H7*C7*EXP(-H7*F7)*_xlfn.NORM.S.DIST(J7,TRUE()))/365 -> -1.1802497 | S7: =(-C7*EXP(-H7*F7)*E7*EXP(-0.5*J7^2)/(2*SQRT(2*PI()*F7))+G7*D7*I7*_xlfn.NORM.S.DIST(-K7,TRUE())-H7*C7*EXP(-H7*F7)*_xlfn.NORM.S.DIST(-J7,TRUE()))/365 -> -0.68498601
B8: Short Call 6625 (closed Apr 9) | C8: 7165.08 | D8: 6625 | E8: 0.1957 | F8: 0.060273973 | G8: 0.043 | H8: 0.013 | I8: =EXP(-G8*F8) -> 0.99741157 | J8: =(LN(C8/D8)+((G8-H8)-0.5*E8^2)*F8)/MAX(E8*SQRT(F8),0.0001) -> 1.6447393 | K8: =J8-E8*SQRT(F8) -> 1.5966935 | L8: =C8*EXP(-H8*F8)*_xlfn.NORM.S.DIST(J8,TRUE())-D8*I8*_xlfn.NORM.S.DIST(K8,TRUE()) -> 558.09394 | M8: =-C8*EXP(-H8*F8)*_xlfn.NORM.S.DIST(-J8,TRUE())+D8*I8*_xlfn.NORM.S.DIST(-K8,TRUE()) -> 6.4777059 | N8: =EXP(-H8*F8)*_xlfn.NORM.S.DIST(J8,TRUE()) -> 0.94924413 | O8: =-EXP(-H8*F8)*_xlfn.NORM.S.DIST(-J8,TRUE()) -> -0.049972616 | P8: =EXP(-H8*F8)*EXP(-0.5*J8^2)/(SQRT(2*PI())*C8*E8*SQRT(F8)) -> 0.00029941485 | Q8: =C8*EXP(-H8*F8)*SQRT(F8)*EXP(-0.5*J8^2)/SQRT(2*PI())/100 -> 1.8131597 | R8: =(-C8*EXP(-H8*F8)*E8*EXP(-0.5*J8^2)/(2*SQRT(2*PI()*F8))-G8*D8*I8*_xlfn.NORM.S.DIST(K8,TRUE())+H8*C8*EXP(-H8*F8)*_xlfn.NORM.S.DIST(J8,TRUE()))/365 -> -1.299716 | S8: =(-C8*EXP(-H8*F8)*E8*EXP(-0.5*J8^2)/(2*SQRT(2*PI()*F8))+G8*D8*I8*_xlfn.NORM.S.DIST(-K8,TRUE())-H8*C8*EXP(-H8*F8)*_xlfn.NORM.S.DIST(-J8,TRUE()))/365 -> -0.77625146
B9: Parity check (put leg) | C9: =ROUND((L7-M7)-(C7*EXP(-H7*F7)-D7*I7),6) -> 0 | D9: Zero confirms C - P = S*exp(-qT) - K*exp(-rT)
B11: MODEL NOTES
B12: 1. Framework: Black-Scholes-Merton for European index options with continuous dividend yield q; discounting at continuously compounded risk-free rate r.
B13: 2. Blue cells are inputs (spot, strike, implied vol, tenor, rates); black cells are live formulas. Change any input to re-price and re-derive Greeks.
B14: 3. Greeks: Delta and Gamma per 1 index point; Vega per 1 vol point (1%); Theta per calendar day. Position Greeks = model Greeks x quantity (short = -1).
B15: 4. Put-call parity holds by construction: C - P = S*exp(-qT) - K*exp(-rT). Row 9 verifies the identity.
B16: 5. This engine generated the daily delta and theta marks in the Daily P&L Monitor throughout the project.

Sheet Trade Blotter
B2: TRADE BLOTTER
B3: All executions at instructor-posted end-of-day marks. SPX index options, May 16, 2026 expiry.
B5: # | C5: Trade Date | D5: Action | E5: Type | F5: Strike | G5: Buy/Sell | H5: Qty | I5: Price ($) | J5: S&P Ref | K5: Realized P&L ($) | L5: Rationale
B6: 1 | C6: 3/27/2026 | D6: OPEN | E6: Put | F6: 6385 | G6: Sell | H6: -1 | I6: 226.2 | J6: 6368.85 | L6: Strangle leg 1: sold 6385 put at entry IV 25.15%. Premium collected $226.20.
B7: 2 | C7: 3/27/2026 | D7: OPEN | E7: Call | F7: 6595 | G7: Sell | H7: -1 | I7: 227.5 | J7: 6368.85 | L7: Strangle leg 2: sold 6595 call at entry IV 20.79%. Both legs open; total premium $453.70.
B8: 3 | C8: 4/6/2026 | D8: ROLL - CLOSE | E8: Call | F8: 6595 | G8: Buy | H8: 1 | I8: 189.66 | J8: 6611.83 | K8: =I7-I8 -> 37.84 | L8: Spot broke above the 6595 strike; delta approaching -0.20 band. Bought back the 6595 call; realized +$37.84 on the leg.
B9: 4 | C9: 4/6/2026 | D9: ROLL - OPEN | E9: Call | F9: 6625 | G9: Sell | H9: -1 | I9: 174.46 | J9: 6611.83 | L9: Rolled up 30 points: sold the 6625 call. Net roll cost $15.20; portfolio delta improved from -0.18 to -0.16 with the new strike ~13 pts OTM.
B10: 5 | C10: 4/9/2026 | D10: CLOSE | E10: Call | F10: 6625 | G10: Buy | H10: 1 | I10: 298.59 | J10: 6824.66 | K10: =I9-I10 -> -124.13 | L10: Risk-reducing close after the Apr 8 ceasefire rally left the call ~200 pts ITM (delta -0.42 vs +/-0.20 policy). Net realized call-side P&L across both legs: -$86.29. Short put retained.
B13: REALIZED / UNREALIZED SUMMARY (AT PROJECT END, APR 24)
B15: Call side - realized (both legs) | C15: =K8+K10 -> -86.29
B16: Put side - unrealized (mark $4.60) | C16: ='Daily P&L Monitor'!G26 -> 221.6
B17: Total portfolio P&L | C17: =C15+C16 -> 135.31

Sheet Daily P&L Monitor
B2: DAILY P&L MONITOR | N2: Entry Premiums
B3: Mark-to-market at instructor-posted EOD prices. Put P&L and totals are live formulas keyed to entry premiums (blue inputs at right). | N3: Put 6385 | O3: 226.2
N4: Call 6595 (initial) | O4: 227.5
B5: Date | C5: S&P Close | D5: DTE | E5: Put 6385 Mark | F5: Call Mark | G5: Put P&L ($) | H5: Call P&L ($) | I5: Total P&L ($) | J5: Port. Delta | K5: Theta/day | L5: Desk Commentary | N5: Call 6625 (roll) | O5: 174.46 | Q5: Put Strike | R5: Call Strike
B6: 46108 | C6: 6368.85 | D6: 50 | E6: 229.82 | F6: 113.9 | G6: =$O$3-E6 -> -3.62 | H6: =$O$4-F6 -> 113.6 | I6: =G6+H6 -> 109.98 | J6: 0.181 | K6: 4 | L6: Opened both legs at EOD marks. Put marginally ITM at initiation - acceptable within the range-bound thesis. Net premium $453.70 collected. | N6: Realized on 6595 leg | O6: 37.84 | Q6: 6385 | R6: 6595
B7: 46109 | C7: 6327 | D7: 49 | E7: 248.21 | F7: 97.69 | G7: =$O$3-E7 -> -22.01 | H7: =$O$4-F7 -> 129.81 | I7: =G7+H7 -> 107.8 | J7: 0.2418 | K7: 3.89 | L7: Index -0.7%; put delta pushed portfolio to +0.24, marginally above the +/-0.20 band. Held: move occurred early in the trade with aggregate P&L still positive; flagged for daily review. | N7: Realized call side (final) | O7: -86.29 | Q7: 6385 | R7: 6595
B8: 46111 | C8: 6343.72 | D8: 47 | E8: 235.73 | F8: 99.29 | G8: =$O$3-E8 -> -9.53 | H8: =$O$4-F8 -> 128.21 | I8: =G8+H8 -> 118.68 | J8: 0.2228 | K8: 4.03 | L8: Index recovered modestly; weekend theta accrued to the book. No action. | Q8: 6385 | R8: 6595
B9: 46112 | C9: 6528.52 | D9: 46 | E9: 154.19 | F9: 171.91 | G9: =$O$3-E9 -> 72.01 | H9: =$O$4-F9 -> 55.59 | I9: =G9+H9 -> 127.6 | J9: -0.0484 | K9: 4.51 | L9: +185 pt rally on Iran peace-deal headlines. Put risk relieved; call now closer to strike but portfolio delta ~0. No action. | Q9: 6385 | R9: 6595
B10: 46113 | C10: 6575.32 | D10: 45 | E10: 135.57 | F10: 181.78 | G10: =$O$3-E10 -> 90.63 | H10: =$O$4-F10 -> 45.72 | I10: =G10+H10 -> 136.35 | J10: -0.1197 | K10: 4.46 | L10: Continued rally; spot within 20 pts of the 6595 call strike. Instructor vol mark lowered to 19.57% - a short-vega tailwind. Roll triggers under evaluation. | Q10: 6385 | R10: 6595
B11: 46114 | C11: 6565 | D11: 44 | E11: 136.93 | F11: 174.24 | G11: =$O$3-E11 -> 89.27 | H11: =$O$4-F11 -> 53.26 | I11: =G11+H11 -> 142.53 | J11: -0.1048 | K11: 4.5 | L11: Modest pullback; delta -0.10, inside the band. Held pending the following week's Iran deadline. | Q11: 6385 | R11: 6595
B12: 46118 | C12: 6611.83 | D12: 40 | E12: 112.96 | F12: 174.46 | G12: =$O$3-E12 -> 113.24 | H12: =$O$6+($O$5-F12) -> 37.84 | I12: =G12+H12 -> 151.08 | J12: -0.1566 | K12: 4.7 | L12: Spot broke above 6595. Executed roll: bought back 6595 call at $189.66 (+$37.84 realized), sold 6625 call at $174.46; net cost $15.20. Delta improved to -0.16 with the new strike ~13 pts OTM. | Q12: 6385 | R12: 6625
B13: 46119 | C13: 6616.85 | D13: 39 | E13: 109.21 | F13: 174.69 | G13: =$O$3-E13 -> 116.99 | H13: =$O$6+($O$5-F13) -> 37.61 | I13: =G13+H13 -> 154.6 | J13: -0.1664 | K13: 4.75 | L13: Late-session recovery on Pakistan-mediated ceasefire proposal; call marginally ITM, delta -0.17. Held into the Iran deadline. P&L at period peak (+$154.60). | Q13: 6385 | R13: 6625
B14: 46120 | C14: 6782.81 | D14: 38 | E14: 65.35 | F14: 271.95 | G14: =$O$3-E14 -> 160.85 | H14: =$O$6+($O$5-F14) -> -59.65 | I14: =G14+H14 -> 101.2 | J14: -0.4226 | K14: 4.47 | L14: Ceasefire announced: S&P +2.5% to 6,783; oil -17%; VIX to 21. Call 158 pts ITM; portfolio delta -0.42, more than 2x past the +/-0.20 limit. No trade executed - deferred one session to confirm the move. Retrospective: policy breach; see Executive Summary. | Q14: 6385 | R14: 6625
B15: 46121 | C15: 6824.66 | D15: 37 | E15: 55.44 | F15: CLOSED | G15: =$O$3-E15 -> 170.76 | H15: =$O$7 -> -86.29 | I15: =G15+H15 -> 84.47 | J15: 0.2031 | K15: 1.97 | L15: Closed the 6625 call at $298.59 to cap directional loss; net realized call-side P&L -$86.29. Short put retained; book now long theta on a single leg, +$170 unrealized on the put. | Q15: 6385 | R15: 6625
B16: 46122 | C16: 6816.89 | D16: 36 | E16: 55.02 | F16: CLOSED | G16: =$O$3-E16 -> 171.18 | H16: =$O$7 -> -86.29 | I16: =G16+H16 -> 84.89 | J16: 0.204 | K16: 2 | L16: Index flat; hot CPI print absorbed. Put decaying on schedule. No action. | Q16: 6385
B17: 46125 | C17: 6886.24 | D17: 33 | E17: 38.58 | F17: CLOSED | G17: =$O$3-E17 -> 187.62 | H17: =$O$7 -> -86.29 | I17: =G17+H17 -> 101.33 | J17: 0.1591 | K17: 1.82 | L17: Peace talks failed and a Hormuz blockade began, yet the index rallied - headline sensitivity fading. Put ~500 pts OTM. No action; theta accrual. | Q17: 6385
B18: 46126 | C18: 6967.38 | D18: 32 | E18: 27.08 | F18: CLOSED | G18: =$O$3-E18 -> 199.12 | H18: =$O$7 -> -86.29 | I18: =G18+H18 -> 112.83 | J18: 0.1208 | K18: 1.56 | L18: S&P +1.2% toward all-time highs; oil -7%, VIX 18. Put mark $27, residual risk minimal. No action. | Q18: 6385
B19: 46127 | C19: 7022.95 | D19: 31 | E19: 20.49 | F19: CLOSED | G19: =$O$3-E19 -> 205.71 | H19: =$O$7 -> -86.29 | I19: =G19+H19 -> 119.42 | J19: 0.0971 | K19: 1.37 | L19: Index through 7,000 to a new all-time high. Put 638 pts OTM at $20. Position in run-off; monitoring only. | Q19: 6385
B20: 46128 | C20: 7041.28 | D20: 30 | E20: 17.82 | F20: CLOSED | G20: =$O$3-E20 -> 208.38 | H20: =$O$7 -> -86.29 | I20: =G20+H20 -> 122.09 | J20: 0.0876 | K20: 1.29 | L20: Another record close. Put $17.82, delta +0.09, theta ~$1.30/day. No action. | Q20: 6385
B21: 46129 | C21: 7126.06 | D21: 29 | E21: 11.4 | F21: CLOSED | G21: =$O$3-E21 -> 214.8 | H21: =$O$7 -> -86.29 | I21: =G21+H21 -> 128.51 | J21: 0.0609 | K21: 1.01 | L21: Strait of Hormuz reopened to non-Iranian shipping; oil -9%, S&P +1.2% to a new ATH, VIX 17. Put 741 pts OTM at $11. No action. | Q21: 6385
B22: 46132 | C22: 7109.14 | D22: 26 | E22: 9.6 | F22: CLOSED | G22: =$O$3-E22 -> 216.6 | H22: =$O$7 -> -86.29 | I22: =G22+H22 -> 130.31 | J22: 0.0549 | K22: 0.99 | L22: Hormuz reopening reversed over the weekend; oil +5%, index modestly lower. Put remains far OTM at $10. No action. | Q22: 6385
B23: 46133 | C23: 7064.01 | D23: 25 | E23: 10.97 | F23: CLOSED | G23: =$O$3-E23 -> 215.23 | H23: =$O$7 -> -86.29 | I23: =G23+H23 -> 128.94 | J23: 0.0625 | K23: 1.11 | L23: Risk-off session as the peace process stalled ahead of ceasefire expiry. Put 679 pts OTM; delta +0.06. No action. | Q23: 6385
B24: 46134 | C24: 7137.9 | D24: 24 | E24: 6.79 | F24: CLOSED | G24: =$O$3-E24 -> 219.41 | H24: =$O$7 -> -86.29 | I24: =G24+H24 -> 133.12 | J24: 0.0421 | K24: 0.84 | L24: Ceasefire extended after prior close; S&P +1.05% to a record. Put mark $6.79. No action. | Q24: 6385
B25: 46135 | C25: 7108.4 | D25: 23 | E25: 7.13 | F25: CLOSED | G25: =$O$3-E25 -> 219.07 | H25: =$O$7 -> -86.29 | I25: =G25+H25 -> 132.78 | J25: 0.0447 | K25: 0.89 | L25: Profit-taking; renewed Mideast tension, oil above $100. Put unaffected at $7. Final session tomorrow. | Q25: 6385
B26: 46136 | C26: 7165.08 | D26: 22 | E26: 4.6 | F26: CLOSED | G26: =$O$3-E26 -> 221.6 | H26: =$O$7 -> -86.29 | I26: =G26+H26 -> 135.31 | J26: 0.031 | K26: 0.68 | L26: PROJECT END. New all-time high 7,165.08 (+0.80%). Put marked $4.60 with 22 days to expiry; VIX 18.7. Final portfolio P&L +$135.31 (~29.8% of premium collected). | Q26: 6385
B28: Delta/theta from the Pricing Model engine at each day's marks. Amber rows = hedge executions (Apr 6 roll, Apr 9 close). Red row = delta-limit breach (Apr 8).

Sheet Performance
B2: PERFORMANCE
B3: Charts reference the Daily P&L Monitor and update automatically with the marks.
B43: Reading: P&L peaked Apr 7 (+$154.60), drew down on the Apr 8 ceasefire rally as the short call went deep ITM, then recovered on put decay after the Apr 9 close - finishing at +$135.31.
