Workbook

Sheet Cover
B5: SPACEX ACQUISITION OF CURSOR
B6: Live M&A Transaction Analysis
B7: $60.0 Billion All-Stock Acquisition of Anysphere, Inc.
B9: Date Prepared: | C9: 46189 | E9: Expected Close: | F9: Q3 2026E
B10: Consideration: | C10: SPCX Class A Shares | E10: Prepared By: | F10: Tejasvi Gupta
B11: Program: | C11: Master of Science in Finance | E11: Purpose: | F11: Investment Banking / M&A Transaction Case Study
B12: Date Prepared: | C12: 46216
C15: TRANSACTION SUMMARY
B17: Purchase Price: | C17: $60.0B | E17: Transaction Type: | F17: All-Stock Acquisition
B18: Exchange Ratio: | C18: 7-Day VWAP Floating Exchange Ratio | E18: Base ARR Assumption: | F18: $2.0B
B19: Implied EV / ARR: | C19: 30.0x | E19: Modeled Closing Probability: | F19: 0.794
B23: Illustrative — Prepared for Educational and Portfolio Purposes Only

Sheet Deal Fact Sheet 
A1: SPACEX ACQUISITION OF CURSOR – DEAL FACT SHEET
A3: Item | B3: Entity/PBID | C3: Value | D3: Units | E3: Source | F3: Confidence | G3: Notes
A4: DEAL TRANSACTION TERMS
A5: Announcement | B5: SpaceX/Anysphere | C5: 46189 | D5: Date | E5: Merger filing / press release | F5: H | G5: Announcement date; use ISO date format.
A6: Acquirer | B6: {=_xll.PBMATCHPBID(C6)} -> 46488-07 | C6: SpaceX | D6: Text | E6: SPCX S-1 / merger filing | F6: H | G6: Acquirer legal/company name.
A7: Acquirer Ticker | B7: {=_xll.PBMATCHPBID(C7)} -> 46488-07 | C7: SPCX | D7: Text | E7: Nasdaq / PitchBook | F7: H | G7: Public ticker.
A8: Target | B8: {=_xll.PBMATCHPBID(C8)} -> 519419-89 | C8: Anysphere | D8: Text | E8: Merger filing / PitchBook | F8: H | G8: Target legal/company name.
A9: Target Product | B9: {=_xll.PBMATCHPBID(C9)} -> 519419-89 | C9: Cursor | D9: Text | E9: Company / press | F9: H/M | G9: Cursor is Anysphere’s core AI coding product.
A10: Deal Status | B10: SpaceX/Anysphere | C10: Announced / Pending Close | D10: Text | E10: Merger filing | F10: H | G10: Deal is announced and pending close, not completed.
A11: Consideration Type | B11: SpaceX/Anysphere | C11: All Stock | D11: Text | E11: Merger agreement | F11: H | G11: All-stock consideration.
A12: Stock Consideration | B12: SPCX | C12: SPCX Class A Shares | D12: Text | E12: Merger agreement | F12: H | G12: Verify exact share class in the agreement.
A13: Headline Transaction Value | B13: SpaceX/Anysphere | C13: 60 | D13: Text | E13: Merger agreement / press release | F13: H | G13: Headline transaction value; do not call this enterprise value unless debt/cash treatment is confirmed.
A14: Exchange Ratio Type | B14: SpaceX/Anysphere | C14: Floating Value/ VWAP– Set Ratio | D14: Text | E14: Merger agreement | F14: H | G14: Value fixed; share count floats based on VWAP-set exchange ratio.
A15: VWAP Measurement Period | B15: SPCX | C15: 7 Trading days Before the Close | D15: Text | E15: Merger agreement | F15: H | G15: Exchange ratio based on 7 trading-day VWAP before close.
A16: Expected Close | B16: SpaceX/Anysphere | C16: Q3 2026 | D16: Text | E16: Merger filing | F16: H | G16: Expected closing period; do not convert to exact date unless disclosed.
A17: Required Approvals | B17: SpaceX/Anysphere | C17: TBD per Filing | D17: Text | E17: Merger agreement | F17: H/M | G17: Replace with exact approvals once confirmed from agreement.
A18: April Option Date | B18: SpaceX/Anysphere | C18: 46133 | D18: Date | E18: Press / agreement if disclosed | F18: M | G18: April option date; upgrade to H only if filing confirms.
A19: Walk-Away Economics | B19: SpaceX/Anysphere | C19: 10 | D19: $B | E19: Press / agreement | F19: M | G19: Reported total walk-away package.
A20: Breakup Fee Component | B20: SpaceX/Anysphere | C20: 1.5 | D20: $B | E20: Press / agreement | F20: M | G20: Reported breakup fee component.
A21: Compute Component | B21: SpaceX/Anysphere | C21: 8.5 | D21: $B | E21: Press / agreement | F21: M/L | G21: Reported compute component; keep lower confidence unless agreement confirms.
A22: Earnout/Retention Disclosure | B22: SpaceX/Anysphere | C22: Non–Disclosed/TBD | D22: Text | E22: Merger agreement | F22: M | G22: Important retention risk if no earnout or special retention package is disclosed.
A23: Form of Seller Proceeds | B23: SpaceX/Anysphere | C23: SPCX Stock | D23: Text | E23: Merger agreement | F23: H | G23: Seller proceeds remain exposed to SPCX stock performance.
A25: PARTIES AND STRATEGIC LOGIC
A26: Strategic Rationale | B26: SpaceX/Anysphere | C26: Product + talent + margin synergy | D26: Text | E26: Model judgment / press synthesis | F26: M | G26: Working strategic thesis; support later with filing and press evidence.
A27: xAI Context | B27: SPCX | C27: xAI folded into SpaceX; coding gap still needs support | D27: Text | E27: Filing / press | F27: M | G27: Use careful sourcing before stating as fact.
A28: Coding Product Gap | B28: SPCX | C28: Grok coding performance gap / Cursor product gap | D28: Text | E28: Press / model judgment | F28: M/L | G28: Do not overstate without direct evidence.
A29: Cursor Strategic Asset | B29: Anysphere | C29: AI coding workflow and developer distribution | D29: Text | E29: Company / press | F29: H/M | G29: Core product rationale.
A30: Margin Trap Thesis | B30: Anysphere | C30: Retail model-API cost exposure / margin improvement opportunity | D30: Text | E30: Press / model judgment | F30: M/L | G30: Margin trap thesis needs source support.
A31: Model Dependency | B31: Anysphere | C31: Anthropic / OpenAI / other model-provider dependency | D31: Text | E31: Product docs / press | F31: M | G31: Verify actual model mix.
A32: Integration Question | B32: SpaceX/Anysphere | C32: Remain model-agnostic vs. xAI-preferred roadmap | D32: Text | E32: Model judgment | F32: M | G32: Key integration and customer-trust issue.
A33: Key Talent Risk | B33: Anysphere | C33: Founder and researcher retention | D33: Text | E33: Model judgment | F33: M | G33: No earnout disclosure makes retention a major diligence item.
A34: Key Commercial Risk | B34: Anysphere | C34: Enterprise churn if Cursor neutrality changes | D34: Text | E34: Model judgment | F34: M | G34: Commercial risk if customers view Cursor as captive to xAI.
A36: CURSOR FUNDING/ARR HISTORY
A37: Target PitchBook ID | B37: {=_xll.PBMATCHPBID($C$8)} -> 519419-89 | C37: Anysphere | D37: Text | E37: PitchBook | F37: H | G37: Use PitchBook company profile ID.
A38: Series C Date | B38: 287345-62T | C38: {=_xll.PBD(B38,"Deal Date","","USD","","")} -> 45813 | D38: Date | E38: PitchBook | F38: H | G38: Use exact financing date from PitchBook.
A39: Series C Amount | B39: 287345-62T | C39: {=_xll.PBD(B39,"Deal Amount","","USD","/1000000000","")} -> 0.89999898 | D39: $B | E39: PitchBook | F39: H | G39: Series C amount from PitchBook financing history.
A40: Series C Post Money | B40: 287345-62T | C40: {=_xll.PBD(B40,"Deal Post Valuation","","USD","/1000000000","")} -> 9.9 | D40: $B | E40: PitchBook | F40: H | G40: Series C post-money valuation from PitchBook.
A41: Late 2025 Round Date | B41: 312975-01T | C41: {=_xll.PBD(B41,"Deal Date","","USD","/1000000000","")} -> 45974 | D41: Date | E41: PitchBook | F41: H | G41: Late-2025 financing date from PitchBook.
A42: Late 2025 Round Amount | B42: 312975-01T | C42: {=_xll.PBD(B42,"Deal Amount","","USD","/1000000000","")} -> 2.3000003 | D42: $B | E42: PitchBook | F42: H | G42: Late-2025 round amount from PitchBook.
A43: Late 2025 Post Money | B43: 312975-01T | C43: {=_xll.PBD(B43,"Deal Post Valuation","","USD","/1000000000","")} -> 29.3 | D43: $B | E43: PitchBook | F43: H/M | G43: Most recent confirmed post-money valuation before acquisition.
A44: Pre-empted Round Amount | B44: {=_xll.PBMATCHPBID($C$8)} -> 519419-89 | C44: 2 | D44: $B | E44: Press | F44: M | G44: Reported proposed/preempted financing round amount; not closed.
A45: Pre-empted Round Valuation | B45: {=_xll.PBMATCHPBID($C$8)} -> 519419-89 | C45: 50 | D45: $B | E45: Press | F45: M | G45: Reported proposed valuation before SpaceX acquisition.
A46: ARR low Case | B46: {=_xll.PBMATCHPBID($C$8)} -> 519419-89 | C46: 1 | D46: $B | E46: Press | F46: M | G46: Low ARR case; press-reported annualized revenue estimate.
A47: ARR Base Case | B47: {=_xll.PBMATCHPBID($C$8)} -> 519419-89 | C47: 2 | D47: $B | E47: Press / model judgment | F47: M | G47: Base ARR placeholder pending source triangulation.
A48: a16z Ownership | B48: {=_xll.PBMATCHPBID($C$8)} -> 519419-89 | C48: 0.1 | D48: % | E48: PitchBook / press | F48: M | G48: Use PitchBook cap table if available.
A49: Thrive Ownership | B49: {=_xll.PBMATCHPBID($C$8)} -> 519419-89 | C49: 0.07 | D49: % | E49: PitchBook / press | F49: M | G49: Use PitchBook cap table if available.
A50: NVIDIA Ownership/ Exposure | B50: {=_xll.PBMATCHPBID($C$8)} -> 519419-89 | C50: TBD | D50: text | E50: PitchBook / press | F50: M | G50: Separate equity ownership from commercial/model or compute exposure.
A51: Founder Proceeds/ Founder | B51: {=_xll.PBMATCHPBID($C$8)} -> 519419-89 | C51: 2.7 | D51: $B | E51: Press / model judgment | F51: M/L | G51: Do not treat as high-confidence unless cap table supports.
E52: Model judgment | F52: M | G52: Spacer or summary row if used later.
A53: VALUATION SNAPSHOT
A54: Headline Transaction Value | B54: Anysphere | C54: =C13 -> 60 | D54: $B | E54: Formula | F54: H | G54: Pulls headline value from transaction terms.
A55: EV/ARR– Low ARR Case | B55: Anysphere | C55: =IFERROR(C54/C46,"N/D") -> 60 | D55: x | E55: Formula | F55: M | G55: Headline value divided by ARR low case.
A56: EV/ARR– Base ARR Case | B56: Anysphere | C56: =IFERROR(C54/C47,"N/D") -> 30 | D56: x | E56: Formula | F56: M | G56: Headline value divided by ARR base case.
A57: EV/ARR– High ARR Case | B57: Anysphere | C57: N/D | D57: x | E57: Model placeholder | F57: L | G57: No separate ARR High Case input row is currently available; add one later in Step 2 if keeping the $4B case.
A58: Premium to late - 2025 Post Money | B58: Anysphere | C58: =IFERROR(C54/C43-1,"N/D") -> 1.0477815 | D58: % | E58: Formula | F58: M | G58: Premium to late-2025 post-money valuation.
A59: Premium to Pre-empted Round Valuation | B59: Anysphere | C59: =IFERROR(C54/C45-1,"N/D") -> 0.2 | D59: % | E59: Formula | F59: M | G59: Premium to reported preempted round valuation.
A60: SpaceX IPO Equity Value | B60: SPCX | C60: TBD | D60: $B | E60: SPCX S-1 / IPO workbook | F60: H/M | G60: Use IPO equity value, not announcement-day market cap.
A61: Dilution vs IPO Equity Value | B61: SPCX | C61: =IFERROR(C54/C60,"N/D") -> N/D | D61: % | E61: Formula | F61: H/M | G61: Approximate dilution versus IPO equity value.
A62: Announcement Market Cap | B62: SPCX | C62: =C71 -> 2658.551 | D62: $B | E62: Formula / PitchBook market data | F62: H/M | G62: References announcement-day market cap from PitchBook Pulls section without editing C71.
A63: Announcement Day Move | B63: SPCX | C63: =IFERROR(C69/C70-1,"N/D") -> 0.048311688 | D63: % | E63: Formula / PitchBook market data | F63: H/M | G63: Announcement close divided by prior-day close minus one.
A64: Market Implied Value Created | B64: SPCX | C64: =IFERROR(C62/(1+C63)*C63,"N/D") -> 122.51994 | D64: $B | E64: Formula | F64: M | G64: Rough market cap increase from announcement move; do not label this as synergy value.
A66: PITCHBOOK PULLS/ MARKET DATA
A67: SpaceX PitchBook ID | B67: SPCX | C67: =B6 -> 46488-07 | D67: Text | E67: IPO workbook / PitchBook | F67: H | G67: SpaceX PitchBook ID from IPO workbook.
A68: Anysphere PitchBook ID | B68: Anysphere | C68: =B8 -> 519419-89 | D68: Text | E68: PitchBook | F68: H | G68: Anysphere PitchBook ID.
A69: Announcement Close Price | B69: SPCX | C69: {=_xll.PBM($C$67,"Close Price","16-Jun-2026","16-Jun-2026","0","d","asc","USD","")} -> 201.8 | D69: $/share | E69: PitchBook Market Data | F69: H/M | G69: SPCX close price on announcement date.
A70: Prior Day Close Price | B70: SPCX | C70: {=_xll.PBM($C$67,"Close Price","15-Jun-2026","15-Jun-2026","0","d","asc","USD","")} -> 192.5 | D70: $/share | E70: PitchBook Market Data | F70: H/M | G70: SPCX close price on prior trading day.
A71: Announcement Day Market Cap | B71: SPCX | C71: {=_xll.PBM(C67,"Market Cap","16-Jun-2026","16-Jun-2026","0","d","asc","USD","/1000000000")} -> 2658.551 | D71: $B | E71: PitchBook Market Data | F71: H/M | G71: Announcement-day market capitalization.
A72: Anysphere Most Recent Post Valuation | B72: Anysphere | C72: {=_xll.PBD(C68,"Most Recent Post Valuation","","USD","/1000000000","")} -> 60 | D72: $B | E72: PitchBook | F72: H/M | G72: Should reconcile to target valuation / most recent post-money field.
A73: Anysphere Total Raised | B73: Anysphere | D73: $B | E73: PitchBook | F73: H | G73: Use PitchBook financing summary.
A74: Anysphere Investor List | B74: Anysphere | D74: Text | E74: PitchBook export / manual paste | F74: H/M | G74: Investor list belongs in detail on a later cap table tab.

Sheet Cursor Valuation 
A1: SPACEX ACQUISITION OF CURSOR – CURSOR VALUATION RECONSTRUCTION
A3: CORE VALUE INPUTS
A4: Metric | B4: Data/Case | C4: Value | D4: Units | E4: Derived Value | F4: Derived Units | G4: Source | H4: Confidence | I4: Notes
A5: Headline Transaction Value | B5: Acquisition | C5: ='Deal Fact Sheet '!C13 -> 60 | D5: $B | G5: Merger agreement / Deal Fact Sheet | H5: H | I5: Headline all-stock transaction value. Do not characterize as enterprise value unless cash and debt treatment is confirmed.
A6: Series C Amount | B6: Series C | C6: ='Deal Fact Sheet '!C39 -> 0.89999898 | D6: $B | G6: PitchBook / Deal Fact Sheet | H6: H | I6: Capital raised in the June 2025 Series C financing.
A7: Series C Post Money Valuation | B7: Series C | C7: ='Deal Fact Sheet '!C40 -> 9.9 | D7: $B | G7: PitchBook / Deal Fact Sheet | H7: H | I7: Series C post-money valuation from PitchBook data already captured on the Deal Fact Sheet.
A8: Late-2025 Round Amount | B8: Late-2025 Round | C8: ='Deal Fact Sheet '!C42 -> 2.3000003 | D8: $B | G8: PitchBook / Deal Fact Sheet | H8: H | I8: This row functions as the late-2025 financing amount based on the workbook’s existing row structure.
A9: Late-2025 Post Money Valuation | B9: Late-2025 Round | C9: ='Deal Fact Sheet '!C43 -> 29.3 | D9: $B | G9: PitchBook / Deal Fact Sheet | H9: H/M | I9: Most recent completed post-money valuation before the proposed financing and acquisition.
A10: Preempted Round Amount | B10: Proposed Round | C10: ='Deal Fact Sheet '!C44 -> 2 | D10: $B | G10: Press / Deal Fact Sheet | H10: M | I10: Reported proposed financing amount that was preempted by the SpaceX transaction. This was not a completed financing.
A11: Preempted Round Valuation | B11: Proposed Round | C11: ='Deal Fact Sheet '!C45 -> 50 | D11: $B | G11: Press / Deal Fact Sheet | H11: M | I11: Reported valuation for the proposed financing that was preempted by the SpaceX acquisition.
A12: ARR Low Case | B12: Low | C12: ='Deal Fact Sheet '!C46 -> 1 | D12: $B | G12: Press / Deal Fact Sheet | H12: M | I12: Low ARR case based on the lower reported annualized revenue estimate.
A13: ARR High Case | B13: High | C13: 4 | D13: $B | G13: Press estimate | H13: L/M | I13: High-end reported ARR estimate. Treat as aggressive until the ARR definition and reporting period are independently verified.
A15: ARR SCENARIO VALUATION
A16: Scenario | B16: ARR ($B) | C16: Headline Value ($B) | D16: Headline Value/ARR | E16: ARR required 20.0x | F16: ARR required 25.0x | G16: Source | H16: Confidence | I16: Notes
A17: Low Case | B17: =$C$12 -> 1 | C17: =$C$5 -> 60 | D17: =IFERROR(C17/B17,"N/D") -> 60 | E17: =IFERROR(C17/20,"N/D") -> 3 | F17: =IFERROR(C17/25,"N/D") -> 2.4 | G17: Press estimate | H17: M | I17: Tests the acquisition value using the low ARR case.
A18: Base Case | B18: ='Deal Fact Sheet '!C47 -> 2 | C18: =$C$5 -> 60 | D18: =IFERROR(C18/B18,"N/D") -> 30 | E18: =IFERROR(C18/20,"N/D") -> 3 | F18: =IFERROR(C18/25,"N/D") -> 2.4 | G18: Press / model judgment | H18: M | I18: Working base case using the ARR base case already captured on the Deal Fact Sheet.
A19: High Case | B19: =$C$13 -> 4 | C19: =$C$5 -> 60 | D19: =IFERROR(C19/B19,"N/D") -> 15 | E19: =IFERROR(C19/20,"N/D") -> 3 | F19: =IFERROR(C19/25,"N/D") -> 2.4 | G19: Press estimate | H19: L/M | I19: Tests the acquisition value using the aggressive high ARR case.
A21: IMPLIED VALUATION AT SELECTED REVENUE MULTIPLES
A22: ARR Scenario | B22: ARR ($B) | C22: 10.0x | D22: 15.0x | E22: 20.0x | F22: 25.0x | G22: 30.0x | H22: Acquisition value($B) | I22: Premium/Discount to (20.0x)
A23: Low Case | B23: =$C$12 -> 1 | C23: =B23*10 -> 10 | D23: =B23*15 -> 15 | E23: =B23*20 -> 20 | F23: =B23*25 -> 25 | G23: =B23*30 -> 30 | H23: =$C$5 -> 60 | I23: =IFERROR(H23/E23-1,"N/D") -> 2
A24: Base Case | B24: ='Deal Fact Sheet '!C47 -> 2 | C24: =B24*10 -> 20 | D24: =B24*15 -> 30 | E24: =B24*20 -> 40 | F24: =B24*25 -> 50 | G24: =B24*30 -> 60 | H24: =$C$5 -> 60 | I24: =IFERROR(H24/E24-1,"N/D") -> 0.5
A25: High Case | B25: =$C$13 -> 4 | C25: =B25*10 -> 40 | D25: =B25*15 -> 60 | E25: =B25*20 -> 80 | F25: =B25*25 -> 100 | G25: =B25*30 -> 120 | H25: =$C$5 -> 60 | I25: =IFERROR(H25/E25-1,"N/D") -> -0.25
A27: FINANCING AND VALUATION
A28: Valuation Milestone | B28: Date | C28: Valuation ($B) | D28: Capital Raised ($B) | E28: Increase vs Prior ($B) | F28: Premium vs Prior | G28: Source | H28: Confidence | I28: Notes
A29: Series C Post–Money | B29: ='Deal Fact Sheet '!C38 -> 45813 | C29: =$C$7 -> 9.9 | D29: =$C$6 -> 0.89999898 | E29: N/A | F29: N/A | G29: PitchBook / Deal Fact Sheet | H29: H | I29: Series C financing benchmark.
A30: Late–2025 Post– Money | B30: ='Deal Fact Sheet '!C41 -> 45974 | C30: =$C$9 -> 29.3 | D30: =$C$8 -> 2.3000003 | E30: =IFERROR(C30-C29,"N/D") -> 19.4 | F30: =IFERROR(C30/C29-1,"N/D") -> 1.959596 | G30: PitchBook / Deal Fact Sheet | H30: H/M | I30: Most recent completed financing valuation before the proposed round and acquisition.
A31: Preempted Round Valuation | B31: Proposed 2026 | C31: =$C$11 -> 50 | D31: =$C$10 -> 2 | E31: =IFERROR(C31-C30,"N/D") -> 20.7 | F31: =IFERROR(C31/C30-1,"N/D") -> 0.70648462 | G31: Press / Deal Fact Sheet | H31: M | I31: Reported proposed financing valuation. The financing was not completed.
A32: SpaceX Acquisition Price | B32: ='Deal Fact Sheet '!C5 -> 46189 | C32: =$C$5 -> 60 | D32: N/A | E32: =IFERROR(C32-C31,"N/D") -> 10 | F32: =IFERROR(C32/C31-1,"N/D") -> 0.2 | G32: Merger agreement / Deal Fact Sheet | H32: H | I32: Headline acquisition value announced on June 16, 2026.
A34: PREMIUM ATTRIBUTION
A35: Premium Component | B35: Starting Value ($B) | C35: Ending Value ($B) | D35: Incremental Value ($B) | E35: Premium | F35: % of Total Uplift | G35: Source | H35: Confidence | I35: Notes
A36: Finance Re-rating | B36: =$C$9 -> 29.3 | C36: =$C$11 -> 50 | D36: =C36-B36 -> 20.7 | E36: =IFERROR(C36/B36-1,"N/D") -> 0.70648462 | F36: =IFERROR(D36/($C$5-$C$9),"N/D") -> 0.6742671 | G36: PitchBook / press | H36: M | I36: Value increase from the last completed financing valuation to the reported proposed financing valuation.
A37: Acquisition Premium | B37: ='Deal Fact Sheet '!C45 -> 50 | C37: =$C$5 -> 60 | D37: =C37-B37 -> 10 | E37: =IFERROR(C37/B37-1,"N/D") -> 0.2 | F37: =IFERROR(D37/($C$5-$C$9),"N/D") -> 0.3257329 | G37: Merger agreement / press | H37: M/H | I37: Incremental acquisition premium above the reported proposed financing valuation.
A38: Total Uplift | B38: =$C$9 -> 29.3 | C38: =$C$5 -> 60 | D38: =C38-B38 -> 30.7 | E38: =IFERROR(C38/B38-1,"N/D") -> 1.0477815 | F38: =SUM(F36:F37) -> 1 | G38: Formula | H38: H/M | I38: Total uplift from the last completed financing valuation to the acquisition value.
A40: FAIR VALUE FRAMEWORK
A41: Case | B41: ARR ($B) | C41: Selected Multiple | D41: Implied Value($B) | E41: Premium / Discount to Deal | F41: Probability Weight | G41: Probability Weighted Value | H41: Confidence | I41: Notes
A42: Downside | B42: =$C$12 -> 1 | C42: 20 | D42: =B42*C42 -> 20 | E42: =IFERROR(D42/$C$5-1,"N/D") -> -0.66666667 | F42: 0.2 | G42: =D42*F42 -> 4 | H42: M | I42: Downside case using the low ARR estimate and a premium growth-software revenue multiple.
A43: Base | B43: ='Deal Fact Sheet '!C47 -> 2 | C43: 25 | D43: =B43*C43 -> 50 | E43: =IFERROR(D43/$C$5-1,"N/D") -> -0.16666667 | F43: 0.5 | G43: =D43*F43 -> 25 | H43: M | I43: Base case using the working ARR estimate and a scarcity and strategic-value premium.
A44: Upside | B44: =$C$13 -> 4 | C44: 20 | D44: =B44*C44 -> 80 | E44: =IFERROR(D44/$C$5-1,"N/D") -> 0.33333333 | F44: 0.3 | G44: =D44*F44 -> 24 | H44: L/M | I44: Upside case using the high ARR estimate and a more normalized premium revenue multiple.
A46: VALUATION CONCLUSION
A47: Conclusion | B47: Value/Statement | C47: Source | D47: Confidence | E47: Notes
A48: Acquisition Multiple– Low ARR | B48: =D17 -> 60 | C48: Formula | D48: M | E48: At the low ARR estimate, the $60.0B transaction implies an exceptionally aggressive revenue multiple and requires very high future growth or substantial strategic synergies.
A49: Acquisition Multiple– Base ARR | B49: =D18 -> 30 | C49: Formula | D49: M | E49: At the base ARR estimate, the transaction implies a 30.0x revenue multiple, which remains aggressive and requires sustained growth, strong retention, and meaningful strategic value.
A50: Acquisition Multiple– High ARR | B50: =D19 -> 15 | C50: Formula | D50: L/M | E50: At the high ARR estimate, the transaction implies a 15.0x revenue multiple, making the price more defensible if the reported $4.0B ARR figure is accurate and comparable.
A51: Premium to Late 2025 Round | B51: =IFERROR($C$5/$C$9-1,"N/D") -> 1.0477815 | C51: Formula | D51: H/M | E51: Measures the total valuation uplift from the late-2025 completed financing valuation to the $60.0B acquisition value. This is not equivalent to a conventional acquisition control premium.
A52: Premium to Preempted Round | B52: =F32 -> 0.2 | C52: Formula | D52: M | E52: Measures the incremental premium paid above the reported $50.0B proposed financing valuation. This is the more relevant measure of the incremental acquisition premium.
A53: ARR required at 20.0x | B53: =E17 -> 3 | C53: Formula | D53: Model | E53: Cursor would require approximately $3.0B of ARR to support the $60.0B acquisition value at a 20.0x revenue multiple.
A54: ARR required at 25.0x | B54: =F17 -> 2.4 | C54: Formula | D54: Model | E54: Cursor would require approximately $2.4B of ARR to support the $60.0B acquisition value at a 25.0x revenue multiple.
A55: Preliminary Fair–Value View | B55: =SUM(G42:G44) -> 53 | C55: Formula / model output | D55: Model | E55: The preliminary probability-weighted fair value is based on the current downside, base, and upside assumptions. It must be updated after completing the trading-comps and precedent-transactions analyses.

Sheet Comps 
A1: SPACEX ACQUISITION OF CURSOR – TRADING COMPARABLES
A3: TRADING COMPARABLE COMPANIES
A4: Company | B4: Ticker | C4: PBID | D4: Market Cap ($B) | E4: EV ($B) | F4: Revenue NTM ($B) | G4: Revenue Growth | H4: EV/Revenue NTM | I4: EBITDA Margin | J4: Rule of 40 | K4: Inclusion Weight | L4: Source | M4: Confidence | N4: Include | O4: Notes
A5: GitLab | B5: {=_xll.PBMATCHSYMBOL(A5)} -> NAS:GTLB | C5: {=_xll.PBMATCHPBID(A5)} -> 84804-13 | D5: {=_xll.PBM(C5,"Market Cap","16-Jun-2026","16-Jun-2026","0","d","asc","USD","/1000000000")} -> 4.697109 | E5: {=_xll.PBF(C5,"EV","NTM","16-Jun-2026","","USD","")/1000000000} -> 3.385826 | F5: {=_xll.PBF(C5,"Total Revenue","NTM","16-Jun-2026","","USD","")/1000000000} -> 1.004873 | G5: {=_xll.PBF(C5,"Revenue % Growth","NTM","16-Jun-2026","","USD","")} -> 0.24895503 | H5: {=_xll.PBF(C5,"EV to Revenue","NTM","16-Jun-2026","","USD","")} -> 3.3694069 | I5: {=_xll.PBF(C5,"EBITDA Margin","NTM","16-Jun-2026","","USD","")} -> -0.052350894 | J5: =IFERROR(G5+I5,"N/D") -> 0.19660414 | K5: 0.2 | L5: PitchBook | M5: H | N5: Y | O5: Closest public developer-tools and DevSecOps comp; directly relevant developer audience and software workflow exposure.
A6: Atlassian | B6: {=_xll.PBMATCHSYMBOL(A6)} -> NAS:TEAM | C6: {=_xll.PBMATCHPBID(A6)} -> 45245-62 | D6: {=_xll.PBM(C6,"Market Cap","16-Jun-2026","16-Jun-2026","0","d","asc","USD","/1000000000")} -> 22.318883 | E6: {=_xll.PBF(C6,"EV","NTM","16-Jun-2026","","USD","")/1000000000} -> 22.425559 | F6: {=_xll.PBF(C6,"Total Revenue","NTM","16-Jun-2026","","USD","")/1000000000} -> 6.190183 | G6: {=_xll.PBF(C6,"Revenue % Growth","NTM","16-Jun-2026","","USD","")} -> 0.24737947 | H6: {=_xll.PBF(C6,"EV to Revenue","NTM","16-Jun-2026","","USD","")} -> 3.622762 | I6: {=_xll.PBF(C6,"EBITDA Margin","NTM","16-Jun-2026","","USD","")} -> -0.01809995 | J6: =IFERROR(G6+I6,"N/D") -> 0.22927952 | K6: 0.15 | L6: PitchBook | M6: H | N6: Y | O6: Scaled developer-collaboration and productivity software platform; relevant product-led growth and developer ecosystem exposure.
A7: Datadog | B7: {=_xll.PBMATCHSYMBOL(A7)} -> NAS:DDOG | C7: {=_xll.PBMATCHPBID(A7)} -> 53904-79 | D7: {=_xll.PBM(C7,"Market Cap","16-Jun-2026","16-Jun-2026","0","d","asc","USD","/1000000000")} -> 82.265959 | E7: {=_xll.PBF(C7,"EV","NTM","16-Jun-2026","","USD","")/1000000000} -> 78.792394 | F7: {=_xll.PBF(C7,"Total Revenue","NTM","16-Jun-2026","","USD","")/1000000000} -> 3.672031 | G7: {=_xll.PBF(C7,"Revenue % Growth","NTM","16-Jun-2026","","USD","")} -> 0.29544323 | H7: {=_xll.PBF(C7,"EV to Revenue","NTM","16-Jun-2026","","USD","")} -> 21.457443 | I7: {=_xll.PBF(C7,"EBITDA Margin","NTM","16-Jun-2026","","USD","")} -> 0.0097058004 | J7: =IFERROR(G7+I7,"N/D") -> 0.30514903 | K7: 0.15 | L7: PitchBook | M7: H | N7: Y | O7: High-growth cloud software company with strong developer and enterprise usage; useful premium software valuation benchmark.
A8: Cloudflare | B8: {=_xll.PBMATCHSYMBOL(A8)} -> NYS:NET | C8: {=_xll.PBMATCHPBID(A8)} -> 52368-49 | D8: {=_xll.PBM(C8,"Market Cap","16-Jun-2026","16-Jun-2026","0","d","asc","USD","/1000000000")} -> 81.980391 | E8: {=_xll.PBF(C8,"EV","NTM","16-Jun-2026","","USD","")/1000000000} -> 81.341049 | F8: {=_xll.PBF(C8,"Total Revenue","NTM","16-Jun-2026","","USD","")/1000000000} -> 2.328605 | G8: {=_xll.PBF(C8,"Revenue % Growth","NTM","16-Jun-2026","","USD","")} -> 0.31551355 | H8: {=_xll.PBF(C8,"EV to Revenue","NTM","16-Jun-2026","","USD","")} -> 34.931235 | I8: {=_xll.PBF(C8,"EBITDA Margin","NTM","16-Jun-2026","","USD","")} -> -0.0051958147 | J8: =IFERROR(G8+I8,"N/D") -> 0.31031773 | K8: 0.1 | L8: PitchBook | M8: H | N8: Y | O8: High-growth infrastructure software platform with strong developer adoption; useful premium-growth benchmark despite different end market.
A9: MongoDB | B9: {=_xll.PBMATCHSYMBOL(A9)} -> NAS:MDB | C9: {=_xll.PBMATCHPBID(A9)} -> 51351-85 | D9: {=_xll.PBM(C9,"Market Cap","16-Jun-2026","16-Jun-2026","0","d","asc","USD","/1000000000")} -> 28.05546 | E9: {=_xll.PBF(C9,"EV","NTM","16-Jun-2026","","USD","")/1000000000} -> 25.658734 | F9: {=_xll.PBF(C9,"Total Revenue","NTM","16-Jun-2026","","USD","")/1000000000} -> 2.602399 | G9: {=_xll.PBF(C9,"Revenue % Growth","NTM","16-Jun-2026","","USD","")} -> 0.23635515 | H9: {=_xll.PBF(C9,"EV to Revenue","NTM","16-Jun-2026","","USD","")} -> 9.8596466 | I9: {=_xll.PBF(C9,"EBITDA Margin","NTM","16-Jun-2026","","USD","")} -> -0.022158401 | J9: =IFERROR(G9+I9,"N/D") -> 0.21419674 | K9: 0.15 | L9: PitchBook | M9: H | N9: Y | O9: Developer-oriented database platform with consumption and enterprise exposure; relevant infrastructure-software comparison.
A10: Snowflake | B10: {=_xll.PBMATCHSYMBOL(A10)} -> NYS:SNOW | C10: {=_xll.PBMATCHPBID(A10)} -> 61489-18 | D10: {=_xll.PBM(C10,"Market Cap","16-Jun-2026","16-Jun-2026","0","d","asc","USD","/1000000000")} -> 82.601712 | E10: {=_xll.PBF(C10,"EV","NTM","16-Jun-2026","","USD","")/1000000000} -> 82.418809 | F10: {=_xll.PBF(C10,"Total Revenue","NTM","16-Jun-2026","","USD","")/1000000000} -> 5.032823 | G10: {=_xll.PBF(C10,"Revenue % Growth","NTM","16-Jun-2026","","USD","")} -> 0.31071257 | H10: {=_xll.PBF(C10,"EV to Revenue","NTM","16-Jun-2026","","USD","")} -> 16.376258 | I10: {=_xll.PBF(C10,"EBITDA Margin","NTM","16-Jun-2026","","USD","")} -> -0.22161201 | J10: =IFERROR(G10+I10,"N/D") -> 0.089100562 | K10: 0.1 | L10: PitchBook | M10: H | N10: Y | O10: High-growth data-cloud platform; useful premium valuation benchmark but less directly comparable to an AI coding product.
A11: Elastic | B11: {=_xll.PBMATCHSYMBOL(A11)} -> NYS:ESTC | C11: {=_xll.PBMATCHPBID(A11)} -> 55574-02 | D11: {=_xll.PBM(C11,"Market Cap","16-Jun-2026","16-Jun-2026","0","d","asc","USD","/1000000000")} -> 6.2485327 | E11: {=_xll.PBF(C11,"EV","NTM","16-Jun-2026","","USD","")/1000000000} -> 5.4698337 | F11: {=_xll.PBF(C11,"Total Revenue","NTM","16-Jun-2026","","USD","")/1000000000} -> 1.739331 | G11: {=_xll.PBF(C11,"Revenue % Growth","NTM","16-Jun-2026","","USD","")} -> 0.17261221 | H11: {=_xll.PBF(C11,"EV to Revenue","NTM","16-Jun-2026","","USD","")} -> 3.1447917 | I11: {=_xll.PBF(C11,"EBITDA Margin","NTM","16-Jun-2026","","USD","")} -> 0.019935826 | J11: =IFERROR(G11+I11,"N/D") -> 0.19254804 | K11: 0.1 | L11: PitchBook | M11: H | N11: Y | O11: Developer and observability-oriented search platform; relevant software infrastructure comparison.
A12: Confluent | B12: {=_xll.PBMATCHSYMBOL(A12)} -> #NOMATCH | C12: {=_xll.PBMATCHPBID(A12)} -> 99264-61 | D12: {=_xll.PBM(C12,"Market Cap","16-Jun-2026","16-Jun-2026","0","d","asc","USD","/1000000000")} -> #N/A | E12: {=_xll.PBF(C12,"EV","NTM","16-Jun-2026","","USD","")/1000000000} -> #N/A | F12: {=_xll.PBF(C12,"Total Revenue","NTM","16-Jun-2026","","USD","")/1000000000} -> 1.166748 | G12: {=_xll.PBF(C12,"Revenue % Growth","NTM","16-Jun-2026","","USD","")} -> 0.21076914 | H12: {=_xll.PBF(C12,"EV to Revenue","NTM","16-Jun-2026","","USD","")} -> #N/A | I12: {=_xll.PBF(C12,"EBITDA Margin","NTM","16-Jun-2026","","USD","")} -> -0.23238266 | J12: =IFERROR(G12+I12,"N/D") -> -0.021613512 | K12: 0 | L12: PitchBook | M12: L | N12: N | O12: Excluded from selected comp statistics under the current Include flag; retain as a reference comp only.
A13: GitHub | B13: {=_xll.PBMATCHSYMBOL(A13)} -> #NOMATCH | C13: {=_xll.PBMATCHPBID(A13)} -> 54525-52 | D13: {=_xll.PBM(C13,"Market Cap","16-Jun-2026","16-Jun-2026","0","d","asc","USD","/1000000000")} -> #N/A | E13: {=_xll.PBF(C13,"EV","NTM","16-Jun-2026","","USD","")/1000000000} -> #N/A | F13: {=_xll.PBF(C13,"Total Revenue","NTM","16-Jun-2026","","USD","")/1000000000} -> #N/A | G13: {=_xll.PBF(C13,"Revenue % Growth","NTM","16-Jun-2026","","USD","")} -> #N/A | H13: {=_xll.PBF(C13,"EV to Revenue","NTM","16-Jun-2026","","USD","")} -> #N/A | I13: {=_xll.PBF(C13,"EBITDA Margin","NTM","16-Jun-2026","","USD","")} -> #N/A | J13: =IFERROR(G13+I13,"N/D") -> N/D | K13: 0 | L13: PitchBook | M13: L | N13: N | O13: Do not include in public trading statistics because GitHub is not a standalone publicly traded company. Use in precedent-transactions analysis instead.
A14: HashiCorp | B14: {=_xll.PBMATCHSYMBOL(A14)} -> #NOMATCH | C14: {=_xll.PBMATCHPBID(A14)} -> 59113-45 | D14: {=_xll.PBM(C14,"Market Cap","16-Jun-2026","16-Jun-2026","0","d","asc","USD","/1000000000")} -> #N/A | E14: {=_xll.PBF(C14,"EV","NTM","16-Jun-2026","","USD","")/1000000000} -> #N/A | F14: {=_xll.PBF(C14,"Total Revenue","NTM","16-Jun-2026","","USD","")/1000000000} -> #N/A | G14: {=_xll.PBF(C14,"Revenue % Growth","NTM","16-Jun-2026","","USD","")} -> #N/A | H14: {=_xll.PBF(C14,"EV to Revenue","NTM","16-Jun-2026","","USD","")} -> #N/A | I14: {=_xll.PBF(C14,"EBITDA Margin","NTM","16-Jun-2026","","USD","")} -> #N/A | J14: =IFERROR(G14+I14,"N/D") -> N/D | K14: 0 | L14: PitchBook | M14: L | N14: N | O14: Do not include in public trading statistics because HashiCorp is not a standalone public trading comp for the selected analysis. Use in precedent-transactions analysis instead.
A16: SUMMARY STATISTICS
A17: Metric | B17: Included Comps | C17: Mean | D17: Median | E17: Minimum | F17: Maximum | G17: Selected | H17: Units | I17: Notes
A18: Revenue Growth | B18: =COUNTIF($N$5:$N$14,"Y") -> 7 | C18: =IFERROR(AVERAGEIF($N$5:$N$14,"Y",$G$5:$G$14),"N/D") -> 0.26099589 | D18: {=IFERROR(MEDIAN(_xlfn._xlws.FILTER($G$5:$G$14,$N$5:$N$14="Y")),"N/D")} -> 0.24895503 | E18: {=IFERROR(MIN(_xlfn._xlws.FILTER($G$5:$G$14,$N$5:$N$14="Y")),"N/D")} -> 0.17261221 | F18: {=IFERROR(MAX(_xlfn._xlws.FILTER($G$5:$G$14,$N$5:$N$14="Y")),"N/D")} -> 0.31551355 | G18: {=IFERROR(SUMPRODUCT(_xlfn._xlws.FILTER($G$5:$G$14,$N$5:$N$14="Y"),_xlfn._xlws.FILTER($K$5:$K$14,$N$5:$N$14="Y"))/SUMIFS($K$5:$K$14,$N$5:$N$14,"Y"),"N/D")} -> 0.25952791 | H18: % | I18: Mean, median, minimum, and maximum include only rows marked Y. Selected represents the normalized inclusion-weighted revenue growth rate.
A19: EV / Revenue NTM | B19: =COUNTIF($N$5:$N$14,"Y") -> 7 | C19: =IFERROR(AVERAGEIF($N$5:$N$14,"Y",$H$5:$H$14),"N/D") -> 13.251649 | D19: {=IFERROR(MEDIAN(_xlfn._xlws.FILTER($H$5:$H$14,$N$5:$N$14="Y")),"N/D")} -> 9.8596466 | E19: {=IFERROR(MIN(_xlfn._xlws.FILTER($H$5:$H$14,$N$5:$N$14="Y")),"N/D")} -> 3.1447917 | F19: {=IFERROR(MAX(_xlfn._xlws.FILTER($H$5:$H$14,$N$5:$N$14="Y")),"N/D")} -> 34.931235 | G19: {=IFERROR(SUMPRODUCT(_xlfn._xlws.FILTER($H$5:$H$14,$N$5:$N$14="Y"),_xlfn._xlws.FILTER($K$5:$K$14,$N$5:$N$14="Y"))/SUMIFS($K$5:$K$14,$N$5:$N$14,"Y"),"N/D")} -> 11.957987 | H19: x | I19: Selected multiple is the normalized inclusion-weighted NTM revenue multiple and will be applied to each Cursor ARR scenario.
A20: EBITDA Margin | B20: =COUNTIF($N$5:$N$14,"Y") -> 7 | C20: =IFERROR(AVERAGEIF($N$5:$N$14,"Y",$I$5:$I$14),"N/D") -> -0.041396491 | D20: {=IFERROR(MEDIAN(_xlfn._xlws.FILTER($I$5:$I$14,$N$5:$N$14="Y")),"N/D")} -> -0.01809995 | E20: {=IFERROR(MIN(_xlfn._xlws.FILTER($I$5:$I$14,$N$5:$N$14="Y")),"N/D")} -> -0.22161201 | F20: {=IFERROR(MAX(_xlfn._xlws.FILTER($I$5:$I$14,$N$5:$N$14="Y")),"N/D")} -> 0.019935826 | G20: {=IFERROR(SUMPRODUCT(_xlfn._xlws.FILTER($I$5:$I$14,$N$5:$N$14="Y"),_xlfn._xlws.FILTER($K$5:$K$14,$N$5:$N$14="Y"))/SUMIFS($K$5:$K$14,$N$5:$N$14,"Y"),"N/D")} -> -0.037621327 | H20: % | I20: Selected value represents the normalized inclusion-weighted EBITDA margin of included trading comps.
A21: Rule of 40 | B21: =COUNTIF($N$5:$N$14,"Y") -> 7 | C21: =IFERROR(AVERAGEIF($N$5:$N$14,"Y",$J$5:$J$14),"N/D") -> 0.2195994 | D21: {=IFERROR(MEDIAN(_xlfn._xlws.FILTER($J$5:$J$14,$N$5:$N$14="Y")),"N/D")} -> 0.21419674 | E21: {=IFERROR(MIN(_xlfn._xlws.FILTER($J$5:$J$14,$N$5:$N$14="Y")),"N/D")} -> 0.089100562 | F21: {=IFERROR(MAX(_xlfn._xlws.FILTER($J$5:$J$14,$N$5:$N$14="Y")),"N/D")} -> 0.31031773 | G21: {=IFERROR(SUMPRODUCT(_xlfn._xlws.FILTER($J$5:$J$14,$N$5:$N$14="Y"),_xlfn._xlws.FILTER($K$5:$K$14,$N$5:$N$14="Y"))/SUMIFS($K$5:$K$14,$N$5:$N$14,"Y"),"N/D")} -> 0.22190659 | H21: % | I21: Rule of 40 equals Revenue Growth plus EBITDA Margin. Selected represents the normalized inclusion-weighted Rule of 40 result.
A23: CURSOR IMPLIED VALUATION
A24: ARR Case | B24: ARR ($B) | C24: Selected Multiple | D24: Implied EV ($B) | E24: Premium/Discount to Deal | F24: Source | G24: Confidence | H24: Notes
A25: Low | B25: ='Cursor Valuation '!C12 -> 1 | C25: =$G$19 -> 11.957987 | D25: =IFERROR(B25*C25,"N/D") -> 11.957987 | E25: =IFERROR(D25/'Cursor Valuation '!C5-1,"N/D") -> -0.80070022 | F25: Trading comps / Cursor Valuation | G25: M | H25: Applies the selected normalized trading-comp NTM revenue multiple to the $1.0B low ARR case.
A26: Base | B26: ='Deal Fact Sheet '!C47 -> 2 | C26: =$G$19 -> 11.957987 | D26: =IFERROR(B26*C26,"N/D") -> 23.915974 | E26: =IFERROR(D26/'Cursor Valuation '!C5-1,"N/D") -> -0.60140044 | F26: Trading comps / Deal Fact Sheet | G26: M | H26: Applies the selected normalized trading-comp NTM revenue multiple to the $2.0B base ARR case.
A27: High | B27: ='Cursor Valuation '!C13 -> 4 | C27: =$G$19 -> 11.957987 | D27: =IFERROR(B27*C27,"N/D") -> 47.831948 | E27: =IFERROR(D27/'Cursor Valuation '!C5-1,"N/D") -> -0.20280087 | F27: Trading comps / Cursor Valuation | G27: L/M | H27: Applies the selected normalized trading-comp NTM revenue multiple to the $4.0B high ARR case. The high ARR estimate remains lower-confidence until independently verified.

Sheet Structure Teardown
A1: SPACEX ACQUISITION OF CURSOR – STRUCTURE TEARDOWN
A3: TRANSACTION STRUCTURE
A4: Metric | B4: Description | C4: Value | D4: Units | E4: Formula | F4: Units | G4: Source | H4: Confidence | I4: Notes
A5: Consideration Type | B5: All-stock acquisition consideration. | C5: All-stock | D5: Text | G5: Merger agreement / Deal Fact Sheet | H5: H | I5: Transaction consideration consists entirely of SPCX equity.
A6: Purchase Price | B6: Headline transaction value. | C6: ='Deal Fact Sheet '!C13 -> 60 | D6: $B | G6: Deal Fact Sheet | H6: H | I6: Headline transaction value announced on 2026-06-16.
A7: Exchange Ratio Type | B7: Floating exchange ratio. | C7: Floating Value | D7: Text | G7: Merger agreement | H7: H | I7: Seller receives a fixed dollar value and a floating number of SPCX shares.
A8: Exchange Ratio Mechanism | B8: Purchase price divided by 7-day SPCX VWAP immediately prior to closing. | C8: Purchase Price / VWAP | D8: Formula Description | G8: Merger agreement | H8: H | I8: Share count adjusts automatically based on SPCX share price.
A9: VWAP Observation Period | B9: Observation window used to calculate share issuance. | C9: 7 | D9: Trading Days | G9: Merger agreement | H9: H | I9: VWAP measured over the seven trading days immediately prior to close.
A10: Closing Share Delivery Mechanism | B10: SPCX Class A shares issued at close. | C10: SPCX Class A | D10: Text | G10: Merger agreement | H10: H | I10: Seller receives newly issued SPCX shares at closing.
A11: Collar Present? | B11: No collar disclosed. | C11: No | D11: Boolean | G11: Merger agreement | H11: H/M | I11: No public disclosure of minimum or maximum exchange ratio protections.
A12: Seller Price Risk | B12: Seller protected from SPCX price declines because share count increases automatically. | C12: Low | D12: Risk Level | G12: Model interpretation | H12: M | I12: Floating value structure protects seller economics.
A13: Acquirer Price Risk | B13: SPCX shareholders bear dilution risk if SPCX trades lower before closing. | C13: High | D13: Risk Level | G13: Model interpretation | H13: M | I13: Lower SPCX share prices require more shares to satisfy the purchase price.
A15: EXCHANGE RATIO MECHANICS
A16: Purchase Price | C16: ='Deal Fact Sheet '!C13 -> 60 | D16: $B | G16: Deal Fact Sheet | H16: H | I16: Headline purchase price.
A17: SPCX VWAP Scenario 1 | C17: 150 | D17: $/share | G17: Scenario Analysis | H17: Model | I17: Illustrative SPCX closing VWAP scenarios.
A18: SPCX VWAP Scenario 2 | C18: 175 | D18: $/share | G18: Scenario Analysis | H18: Model | I18: Illustrative SPCX closing VWAP scenarios.
A19: SPCX VWAP Scenario 3 | C19: 200 | D19: $/share | G19: Scenario Analysis | H19: Model | I19: Illustrative SPCX closing VWAP scenarios.
A20: SPCX VWAP Scenario 4 | C20: 225 | D20: $/share | G20: Scenario Analysis | H20: Model | I20: Illustrative SPCX closing VWAP scenarios.
A21: Shares Issued Scenario 1 | E21: 400 | F21: MM Shares | G21: Model calculation | H21: H | I21: Higher dilution under downside share-price scenario.
A22: Shares Issued Scenario 2 | E22: 342.9 | F22: MM Shares | G22: Model calculation | H22: H | I22: Moderate dilution under base scenario.
A23: Shares Issued Scenario 3 | E23: 300 | F23: MM Shares | G23: Model calculation | H23: H | I23: Reduced dilution if SPCX performs strongly before close.
A24: Shares Issued Scenario 4 | E24: 266.7 | F24: MM Shares | G24: Model calculation | H24: H | I24: Lowest dilution scenario.
A26: FLOATING VS FIXED EXCHANGE RATIO
A27: Metric | B27: Fixed Ratio | C27: Fixed Value | D27: Floating Value | E27: Floating Value with Collar
A28: Seller Downside Protection | B28: Low | C28: High | D28: High | E28: Medium
A29: Seller Upside Participation | B29: High | C29: Low | D29: Low | E29: Medium
A30: Buyer Dilution Certainty | B30: High | C30: Low | D30: Low | E30: Medium
A31: Buyer Price Certainty | B31: Low | C31: High | D31: Low | E31: Medium
A32: Typical Use Case | B32: Large strategic mergers. | C32: Cash acquisitions. | D32: Stock acquisitions. | E32: Mega-cap strategic acquisitions.
A33: SPCX – Cursor Structure | B33: No | C33: No | D33: Yes | E33: No
A35: OPTION ECONOMICS
A36: Option Date | C36: 46133 | D36: Date | G36: Deal Fact Sheet / press | H36: M
A37: Strike Value | C37: 60 | D37: $B | G37: Deal Fact Sheet / press | H37: M
A38: Acquisition Value | C38: ='Deal Fact Sheet '!C13 -> 60 | D38: $B | G38: Deal Fact Sheet / press | H38: M
A39: Walk Away Cost | C39: 10 | D39: $B | G39: Deal Fact Sheet / press | H39: M
A40: Effective Option Value | E40: =C38-C39 -> 50 | F40: $B | G40: Deal Fact Sheet / press | H40: M
A41: Option Value As % of Deal | E41: =E40/C38 -> 0.83333333 | F41: % | G41: Deal Fact Sheet / press | H41: M
A43: BREAKUP ECONOMICS
A44: Breakup Fee | C44: 1.5 | D44: $B | G44: Deal Fact Sheet / press | H44: M
A45: Compute Commitment | C45: 8.5 | D45: $B | G45: Deal Fact Sheet / press | H45: M
A46: Total Walkaway Cost | E46: =C44+C45 -> 10 | F46: $B | G46: Deal Fact Sheet / press | H46: M
A47: Walkaway Cost as % of Purchase Price | E47: =E46/'Deal Fact Sheet '!C13 -> 0.16666667 | F47: % | G47: Deal Fact Sheet / press | H47: M
A49: DiLUTION ANALYSIS
A50: Purchase Price | C50: ='Deal Fact Sheet '!C13 -> 60 | D50: $B | G50: Deal Fact Sheet / model | H50: M
A51: SPCX Equity Value | C51: 2536.03 | D51: $B | G51: Deal Fact Sheet / model | H51: M
A52: Implied Dilution | E52: =C50/C51 -> 0.023659026 | F52: % | G52: Deal Fact Sheet / model | H52: M | I52: Approximate dilution implied by acquisition value divided by SPCX equity value.
A53: Shares Issued at Base VWAP | E53: 300 | F53: MM Shares | G53: Deal Fact Sheet / model | H53: M | I53: Uses the $200 VWAP scenario as the base case.
A55: RETENTION STRUCTURE
A56: Earnout Present? | C56: No | D56: Text | G56: Merger agreement / model interpretation | H56: M
A57: Founder Lockup | C57: Unknown | D57: Text | G57: Merger agreement / model interpretation | H57: M
A58: Equity Rollover | C58: Yes | D58: Text | G58: Merger agreement / model interpretation | H58: M
A59: Employee Retention Pool | C59: Unknown | D59: Text | G59: Merger agreement / model interpretation | H59: M
A60: Integration Risk Score | C60: High | D60: Text | G60: Merger agreement / model interpretation | H60: M
A62: STRUCTURAL CONCLUSIONS
A63: Seller Protected from SPCX Downside | C63: TRUE | D63: Boolean | G63: Model interpretation | H63: M | I63: Seller economics remain largely protected from SPCX downside volatility.
A64: SPCX Shareholders Bear Dilution | C64: TRUE | D64: Boolean | G64: Model interpretation | H64: M | I64: SPCX shareholders absorb dilution if share prices decline.
A65: SPCX Rally Reduces Dilution | C65: TRUE | D65: Boolean | G65: Model interpretation | H65: M | I65: Higher SPCX prices reduce shares issued and therefore dilution.
A66: April Option Highly Valuable | C66: TRUE | D66: Boolean | G66: Model interpretation | H66: M | I66: The April option provided substantial economic value to SpaceX.
A67: No Earnout Increases Retention Risk | C67: TRUE | D67: Boolean | G67: Model interpretation | H67: M | I67: Absence of earnout provisions increases long-term retention risk.

Sheet Dilution Market
A1: SPACEX ACQUISITION OF CURSOR – DILUTION MARKET
A3: Metric | B3: PBID | C3: Value | D3: Units | E3: Source | F3: Confidence | G3: Notes
A4: DEAL DILUTION
A5: Purchase Price | C5: ='Deal Fact Sheet '!C13 -> 60 | D5: $B | E5: Deal Fact Sheet | F5: H | G5: Headline acquisition value.
A6: SPCX Equity Value At Announcement | B6: ='Deal Fact Sheet '!B6 -> 46488-07 | C6: {=_xll.PBM(B6,"Market Cap","15-Jun-2026","15-Jun-2026","0","d","asc","USD","/1000000000")} -> 2536.0311 | D6: $B | E6: PitchBook Market Data | F6: H/M | G6: Announcement-day SPCX market capitalization.
A7: Implied Shares Issued | B7: {=_xll.PBMATCHPBID('Deal Fact Sheet '!C7)} -> 46488-07 | C7: 297.3 | D7: MM Shares | E7: Model | F7: M | G7: Illustrative shares issued using announcement share price.
A8: Dilution % | B8: {=_xll.PBMATCHPBID('Deal Fact Sheet '!C7)} -> 46488-07 | C8: =IFERROR(C5/C6,"N/D") -> 0.023659016 | D8: % | E8: Model | F8: H/M | G8: Purchase price divided by SPCX market capitalization.
A9: Ownership Retained By Legacy SPCX Holders | B9: {=_xll.PBMATCHPBID('Deal Fact Sheet '!C7)} -> 46488-07 | C9: =IFERROR(1-C8,"N/D") -> 0.97634098 | D9: % | E9: Model | F9: H/M | G9: Ownership retained by legacy SPCX shareholders.
A11: MARKET REACTION
A12: SPCX Close Before Announcement | B12: {=_xll.PBMATCHPBID('Deal Fact Sheet '!C7)} -> 46488-07 | C12: {=_xll.PBM(B12,"Close Price","15-Jun-2026","15-Jun-2026","0","d","asc","USD","")} -> 192.5 | D12: $/share | E12: PitchBook Market Data | F12: H/M | G12: SPCX closing price immediately before announcement.
A13: SPCX Close After Announcement | B13: {=_xll.PBMATCHPBID('Deal Fact Sheet '!C7)} -> 46488-07 | C13: {=_xll.PBM(B13,"Close Price","16-Jun-2026","16-Jun-2026","0","d","asc","USD","")} -> 201.8 | D13: $/share | E13: PitchBook Market Data | F13: H/M | G13: SPCX closing price immediately after announcement.
A14: Daily change | B14: {=_xll.PBMATCHPBID('Deal Fact Sheet '!C7)} -> 46488-07 | C14: =IFERROR(C13/C12-1,"N/D") -> 0.048311688 | D14: % | E14: Formula | F14: H | G14: Announcement-day stock price reaction.
A15: Market Cap Before Announcement | B15: {=_xll.PBMATCHPBID('Deal Fact Sheet '!C7)} -> 46488-07 | C15: {=_xll.PBM(B15,"Market Cap","15-Jun-2026","15-Jun-2026","0","d","asc","USD","/1000000000")} -> 2536.0311 | D15: $B | E15: PitchBook Market Data | F15: H/M | G15: SPCX market capitalization immediately before announcement.
A16: Market Cap After Announcement | B16: {=_xll.PBMATCHPBID('Deal Fact Sheet '!C7)} -> 46488-07 | C16: {=_xll.PBM(B16,"Market Cap","16-Jun-2026","16-Jun-2026","0","d","asc","USD","/1000000000")} -> 2658.551 | D16: $B | E16: PitchBook Market Data | F16: H/M | G16: SPCX market capitalization immediately after announcement.
A17: Market Cap Change | B17: {=_xll.PBMATCHPBID('Deal Fact Sheet '!C7)} -> 46488-07 | C17: =IFERROR(C16-C15,"N/D") -> 122.51994 | D17: $B | E17: Formula | F17: H | G17: Announcement-day market capitalization increase.
A19: IMPLIED VALUE CREATION
A20: Market Cap Increase | B20: {=_xll.PBMATCHPBID('Deal Fact Sheet '!$C$7)} -> 46488-07 | C20: =C17 -> 122.51994 | D20: $B | E20: Formula | F20: H | G20: Market capitalization increase attributable to market reaction.
A21: Purchase Price | B21: {=_xll.PBMATCHPBID('Deal Fact Sheet '!$C$7)} -> 46488-07 | C21: =C5 -> 60 | D21: $B | E21: Deal Fact Sheet | F21: H | G21: Acquisition purchase price.
A22: Implied Net Value Creation | B22: {=_xll.PBMATCHPBID('Deal Fact Sheet '!$C$7)} -> 46488-07 | C22: =IFERROR(C20-C21,"N/D") -> 62.519942 | D22: $B | E22: Formula | F22: M | G22: Market capitalization increase minus transaction value.
A23: Value Creation as % of Purchase Price | B23: {=_xll.PBMATCHPBID('Deal Fact Sheet '!$C$7)} -> 46488-07 | C23: =IFERROR(C22/C21,"N/D") -> 1.041999 | D23: % | E23: Formula | F23: M | G23: Net value creation relative to purchase price.
A25: SHAREHOLDER IMPACT
A26: Ownership Dilution | B26: {=_xll.PBMATCHPBID('Deal Fact Sheet '!$C$7)} -> 46488-07 | C26: =C8 -> 0.023659016 | D26: % | E26: Formula | F26: H | G26: Mechanical ownership dilution.
A27: Economic Dilution | B27: {=_xll.PBMATCHPBID('Deal Fact Sheet '!$C$7)} -> 46488-07 | C27: =IFERROR(C26-C23,"N/D") -> -1.01834 | D27: % | E27: Formula | F27: M | G27: Ownership dilution adjusted for market-implied value creation.
A28: Market-Implied Value Change | B28: {=_xll.PBMATCHPBID('Deal Fact Sheet '!$C$7)} -> 46488-07 | C28: =C22 -> 62.519942 | D28: $B | E28: Formula | F28: M | G28: Value created or destroyed according to market reaction.
A29: Net Shareholder Outcome | B29: {=_xll.PBMATCHPBID('Deal Fact Sheet '!$C$7)} -> 46488-07 | C29: =IF(C28>0,"Positive","Negative") -> Positive | D29: Text | E29: Formula | F29: M | G29: Overall shareholder outcome.
A31: CONCLUSION
A32: Deal was Ownership dilutive | B32: {=_xll.PBMATCHPBID('Deal Fact Sheet '!$C$7)} -> 46488-07 | C32: =IF(C8>0,TRUE,FALSE) -> TRUE | D32: Boolean | E32: Formula | F32: H | G32: The transaction is mechanically dilutive.
A33: Market reaction offset dilution | B33: {=_xll.PBMATCHPBID('Deal Fact Sheet '!$C$7)} -> 46488-07 | C33: =IF(C23>0,TRUE,FALSE) -> TRUE | D33: Boolean | E33: Formula | F33: M | G33: Positive market reaction offsets some or all dilution.
A34: Market viewed acquisition positively | B34: {=_xll.PBMATCHPBID('Deal Fact Sheet '!$C$7)} -> 46488-07 | C34: =IF(C17>0,TRUE,FALSE) -> TRUE | D34: Boolean | E34: Formula | F34: M | G34: Market viewed the acquisition positively.
A35: Market cap move exceeded purchase price | B35: {=_xll.PBMATCHPBID('Deal Fact Sheet '!$C$7)} -> 46488-07 | C35: =IF(C17>C5,TRUE,FALSE) -> TRUE | D35: Boolean | E35: Formula | F35: L/M | G35: Market capitalization increase exceeded purchase price.
A36: Market-Implied Value Change (not verified synergy) | B36: {=_xll.PBMATCHPBID('Deal Fact Sheet '!$C$7)} -> 46488-07 | C36: =C22 -> 62.519942 | D36: $B | E36: Formula | F36: M | G36: Announcement-day market capitalisation change less purchase price. This reflects market expectations, not quantified synergies.

Sheet Startegies Synergies
A1: SPACEX ACQUISITION OF CURSOR – STRATEGIES SYNERGIES
A3: Synergy/Risk Item | B3: Category | C3: Mechanism | D3: Financial Driver | E3: Timing | F3: Quantifiable | G3: Confidence
A4: STRATEGIC RATIONALE
A5: AI Coding Product Acquisition | B5: Product | C5: Acquire an established AI coding product instead of building the full product and user base internally. | D5: Time to market / avoided development cost | E5: Near term | F5: Partial | G5: M
A6: Developer Distribution | B6: Revenue / Distribution | C6: Gain direct access to Cursor’s developer users and enterprise engineering teams. | D6: User growth / enterprise revenue | E6: Near term | F6: Partial | G6: M
A7: xAI Product Gap | B7: Product | C7: Use Cursor to accelerate xAI’s position in AI-assisted software development and address a product capability gap. | D7: Product adoption / revenue growth | E7: Medium term | F7: Partial | G7: M/L
A8: Model and Compute Integration | B8: Technology / Margin | C8: Integrate Cursor with xAI models and internal compute infrastructure to improve model economics and product performance. | D8: Gross margin / product quality | E8: Medium term | F8: Yes | G8: M
A9: Enterprise Ai Platform | B9: Revenue | C9: Use Cursor as an enterprise distribution channel for xAI models, APIs, compute, and related software products. | D9: Cross-sell revenue / customer penetration | E9: Medium term | F9: Partial | G9: M/L
A10: Talent Acquistion | B10: Talent | C10: Acquire Cursor’s founders, researchers, product engineers, and developer-tools expertise. | D10: R&D productivity / product execution | E10: Near term | F10: No | G10: M
A11: Startegic Control | B11: Strategy | C11: Obtain control over Cursor’s product roadmap, customer interface, and model-selection strategy. | D11: Strategic control / avoided dependency | E11: Near term | F11: No | G11: M
A12: Competitive Defense | B12: Strategy | C12: Prevent a competing model provider, hyperscaler, or strategic buyer from acquiring Cursor. | D12: Avoided competitive loss | E12: Near term | F12: No | G12: L/M
A14: REVENUE SYNERGIES
A15: Cursor User Growth | B15: Revenue | C15: Use SpaceX and xAI brand, distribution, capital, and product resources to accelerate Cursor user acquisition. | D15: Incremental users × annual revenue per user | E15: Near term | F15: Yes | G15: M
A16: Enterprise Cross-Sell | B16: Revenue | C16: Sell Cursor into SpaceX, Starlink, xAI, government, and enterprise customer relationships. | D16: Enterprise customers × annual contract value | E16: Medium term | F16: Yes | G16: M
A17: xAi Model Upsell | B17: Revenue | C17: Offer premium xAI-powered coding models, agents, or usage tiers inside Cursor. | D17: Paid attach rate × incremental ARPU | E17: Medium term | F17: Yes | G17: M/L
A18: Bundled Enterprise Offering | B18: Revenue | C18: Bundle Cursor with xAI APIs, compute capacity, enterprise support, and other AI services. | D18: Bundle customers × bundle contract value | E18: Medium term | F18: Partial | G18: M/L
A19: International Expansion | B19: Revenue | C19: Use SpaceX’s global commercial footprint to expand Cursor adoption internationally. | D19: International users × annual revenue per user | E19: Medium term | F19: Partial | G19: M/L
A20: Government/Defense Coding | B20: Revenue | C20: Develop secure or private Cursor deployments for government, aerospace, and defense customers. | D20: Contract count × average contract value | E20: Long term | F20: Partial | G20: L/M
A21: Developer Ecosystem Monetization | B21: Revenue | C21: Monetize developer extensions, agents, integrations, marketplaces, or platform services. | D21: Platform activity × take rate | E21: Long term | F21: Partial | G21: L
A23: REVENUE SYNERGY FRAMEWORK
A24: REVENUE SYNERGY | B24: Addressable Base | C24: Adoption/Attch Rate | D24: Incremental Revenue Per Unit | E24: Annual Gross Revenue Synergy ($B) | G24: Probability | H24: Probability Weighted Revenue | I24: Confidence | J24: Notes
A25: Enterprise Cross Sell | B25: 500 | C25: 0.1 | D25: 0.005 | E25: =IF(OR(B25="",C25="",D25=""),"N/D",B25*C25*D25) -> 0.25 | G25: 0.5 | H25: =IF(OR(E25="N/D",G25=""),"N/D",E25*G25) -> 0.125 | I25: M | J25: Illustrative enterprise cross-sell assumption: 500 addressable enterprise relationships, 10.0% adoption, and $5.0 million of incremental annual revenue per converted customer.
A26: Premium xAi Model Upsell | B26: ='Deal Fact Sheet '!C47 -> 2 | C26: 0.2 | D26: 0.2 | E26: =IF(OR(B26="",C26="",D26=""),"N/D",B26*C26*D26) -> 0.08 | G26: 0.6 | H26: =IF(OR(E26="N/D",G26=""),"N/D",E26*G26) -> 0.048 | I26: M/L | J26: Uses the $2.0B base ARR case as the addressable revenue base. Assumes 20.0% premium-feature adoption and a 20.0% incremental revenue uplift.
A27: International Exapansion | B27: 1 | C27: 0.3 | D27: 1 | E27: =IF(OR(B27="",C27="",D27=""),"N/D",B27*C27*D27) -> 0.3 | G27: 0.45 | H27: =IF(OR(E27="N/D",G27=""),"N/D",E27*G27) -> 0.135 | I27: M/L | J27: Illustrative $1.0B international addressable revenue base with 30.0% penetration. The 1.0 factor converts adopted revenue directly into incremental revenue.
A28: Government/Defense Offering | B28: 20 | C28: 0.25 | D28: 0.025 | E28: =IF(OR(B28="",C28="",D28=""),"N/D",B28*C28*D28) -> 0.125 | G28: 0.35 | H28: =IF(OR(E28="N/D",G28=""),"N/D",E28*G28) -> 0.04375 | I28: L/M | J28: Illustrative government and defense opportunity based on 20 addressable contracts, 25.0% conversion, and $25.0 million of annual revenue per converted contract.
A30: COST AND MARGIN SYNERGIES
A31: Model API Cost Reduction | B31: Gross Margin | C31: Shift eligible Cursor usage from retail third-party model API pricing toward internal xAI models or improved negotiated economics. | D31: Model inference spend × savings rate | E31: Near / Medium | F31: Yes | G31: M
A32: Colossus Compute Utilization | B32: Gross Margin | C32: Use xAI compute infrastructure to reduce external compute dependency and lower unit inference costs. | D32: Compute volume × unit-cost reduction | E32: Medium term | F32: Yes | G32: M
A33: Vendor Negotiation Leverage | B33: Gross Margin | C33: Use the combined company’s scale to negotiate improved pricing with third-party model and infrastructure vendors. | D33: Vendor spend × savings rate | E33: Near term | F33: Yes | G33: M/L
A34: Shared R&D Infrastructure | B34: Opex | C34: Consolidate model evaluation, infrastructure tooling, security, safety, and selected engineering resources. | D34: Avoided duplicate headcount and systems | E34: Medium term | F34: Partial | G34: M/L
A35: Shared Sales Infrastructure | B35: Opex / Revenue | C35: Use existing enterprise sales relationships and account coverage to support Cursor distribution. | D35: Avoided sales cost / incremental bookings | E35: Medium term | F35: Partial | G35: M/L
A36: Shared Coporate Function | B36: Opex | C36: Consolidate selected finance, legal, HR, security, procurement, and administrative functions. | D36: Avoided corporate costs | E36: Medium term | F36: Yes | G36: M
A37: Reduced Customer Acquisition Cost | B37: Sales Efficiency | C37: Use SpaceX and xAI distribution to reduce the incremental cost of acquiring new Cursor customers. | D37: New customers × customer acquisition cost reduction | E37: Medium term | F37: Partial | G37: M/L
A38: Reduced Standalone Funding Need | B38: Financing / Strategy | C38: Remove Cursor’s dependence on repeated external private financing and improve access to long-term capital and compute. | D38: Avoided financing friction / funding certainty | E38: Near term | F38: No | G38: M
A40: QUANTIFIED SYNERGY FRAMEWORK
A42: COST SYNERGY FRAMEWORK
A43: Cost Synergy | B43: Adressable Cost Base ($B) | D43: Savings Rate | E43: Annual Gross Savings ($B) | G43: Ramp Year | H43: Probability | I43: Probability Weighted Savings ($B) | J43: Confidence | K43: Notes
A44: Model API Cost Reduction | B44: 0.8 | D44: 0.2 | E44: =IF(OR(B44="",D44=""),"N/D",B44*D44) -> 0.16 | G44: 2 | H44: 0.6 | I44: =IF(OR(E44="N/D",H44=""),"N/D",E44*H44) -> 0.096 | J44: M | K44: Illustrative model-API cost base and savings rate. Assumes savings begin materially in Year 2 as eligible workloads migrate to internal or lower-cost model economics.
A45: Compute Infrastructure Savings | B45: 0.4 | D45: 0.15 | E45: =IF(OR(B45="",D45=""),"N/D",B45*D45) -> 0.06 | G45: 3 | H45: 0.5 | I45: =IF(OR(E45="N/D",H45=""),"N/D",E45*H45) -> 0.03 | J45: M/L | K45: Illustrative compute cost base. Assumes benefits ramp in Year 3 because infrastructure migration and workload optimization require time.
A46: Vendor Negotiation Savings | B46: 0.3 | D46: 0.1 | E46: =IF(OR(B46="",D46=""),"N/D",B46*D46) -> 0.03 | G46: 1 | H46: 0.6 | I46: =IF(OR(E46="N/D",H46=""),"N/D",E46*H46) -> 0.018 | J46: M/L | K46: Illustrative third-party vendor spend and negotiated savings rate. Procurement benefits may begin relatively quickly following closing.
A47: Shared R&D/ Corporate Opex | B47: 0.5 | D47: 0.08 | E47: =IF(OR(B47="",D47=""),"N/D",B47*D47) -> 0.04 | G47: 2 | H47: 0.5 | I47: =IF(OR(E47="N/D",H47=""),"N/D",E47*H47) -> 0.02 | J47: M/L | K47: Illustrative addressable R&D and corporate cost base. Savings reflect limited consolidation rather than broad headcount reduction.
A48: Sales and Distribution Effieciency | B48: 0.4 | D48: 0.1 | E48: =IF(OR(B48="",D48=""),"N/D",B48*D48) -> 0.04 | G48: 3 | H48: 0.4 | I48: =IF(OR(E48="N/D",H48=""),"N/D",E48*H48) -> 0.016 | J48: L/M | K48: Illustrative sales and distribution cost base. Benefits depend on successful use of SpaceX and xAI enterprise relationships.
A50: INTEGRATION COSTS AND DIS – SYNERGIES
A51: Founder departure | B51: Talent Risk | C51: Founders may have reduced incentive to remain after receiving substantial value in SPCX shares. | D51: Product execution / revenue retention | E51: Near / Medium | F51: Partial | G51: M
A52: Key Employee Attrition | B52: Talent Risk | C52: Researchers and engineers may leave following the change of control or cultural integration. | D52: Replacement cost / product delays | E52: Near term | F52: Yes | G52: M
A53: Loss of Model Neutrality | B53: Commercial Risk | C53: Customers may perceive Cursor as biased toward xAI rather than remaining model-neutral. | D53: Customer churn / lower new bookings | E53: Near / Medium | F53: Partial | G53: M
A54: Anthropic/ Open AI Relationship Risk | B54: Vendor Risk | C54: Anthropic or OpenAI may change pricing, access, product support, or strategic cooperation following the acquisition. | D54: Gross margin / product quality / availability | E54: Near term | F54: Partial | G54: M/L
A55: Enterprise Customer Churn | B55: Commercial Risk | C55: Enterprise customers may reduce usage because of ownership, privacy, procurement, or model-neutrality concerns. | D55: Revenue churn / slower sales cycles | E55: Near term | F55: Yes | G55: M/L
A56: Integration Distraction | B56: Execution Risk | C56: Management attention may shift from product velocity toward transaction closing and integration activities. | D56: Delayed launches / lower productivity | E56: Near term | F56: Partial | G56: M
A57: Cultural Integration | B57: Execution Risk | C57: Cursor’s startup culture may conflict with SpaceX or xAI management practices and operating intensity. | D57: Employee retention / productivity | E57: Medium term | F57: No | G57: M
A58: Data Security/Trust | B58: Commercial Risk | C58: Customers may question source-code privacy, data use, model training practices, or information-security controls. | D58: Customer churn / slower enterprise adoption | E58: Near term | F58: Partial | G58: M
A59: Third–Party Model Cost Persistence | B59: Margin Risk | C59: Cursor may need to retain premium third-party models if xAI alternatives do not provide comparable coding performance. | D59: Lower-than-expected cost savings | E59: Medium term | F59: Yes | G59: M
A61: NET SYNERGY VALUE FRAMEWORK
A62: METRIC | B62: YEAR 1 | C62: YEAR 2 | D62: YEAR 3 | E62: YEAR 4 | F62: YEAR 5 | G62: Terminal /Total | H62: Confidence | I62: Notes
A63: Revenue Synergies | B63: =IF($G63="N/D","N/D",$G63*25%) -> 0.0879375 | C63: =IF($G63="N/D","N/D",$G63*50%) -> 0.175875 | D63: =IF($G63="N/D","N/D",$G63*75%) -> 0.2638125 | E63: =IF($G63="N/D","N/D",$G63) -> 0.35175 | F63: =IF($G63="N/D","N/D",$G63) -> 0.35175 | G63: =IF(COUNT(H25:H28)=0,"N/D",SUM(H25:H28)) -> 0.35175 | H63: M/L | I63: Steady-state probability-weighted revenue synergy based on the revenue synergy framework.
A64: Revenue Synergy Gross Profit | B64: =IF(B63="N/D","N/D",B63*80%) -> 0.07035 | C64: =IF(C63="N/D","N/D",C63*80%) -> 0.1407 | D64: =IF(D63="N/D","N/D",D63*80%) -> 0.21105 | E64: =IF(E63="N/D","N/D",E63*80%) -> 0.2814 | F64: =IF(F63="N/D","N/D",F63*80%) -> 0.2814 | G64: =IF(COUNT(B64:F64)=0,"N/D",SUM(B64:F64)) -> 0.9849 | H64: M/L | I64: Revenue synergy gross profit calculated using an illustrative 80.0% gross-margin assumption. Reassess during final workbook review.
A65: Cost Synergy | B65: =IF($G65="N/D","N/D",$G65*25%) -> 0.045 | C65: =IF($G65="N/D","N/D",$G65*50%) -> 0.09 | D65: =IF($G65="N/D","N/D",$G65*75%) -> 0.135 | E65: =IF($G65="N/D","N/D",$G65) -> 0.18 | F65: =IF($G65="N/D","N/D",$G65) -> 0.18 | G65: =IF(COUNT(I44:I48)=0,"N/D",SUM(I44:I48)) -> 0.18 | H65: M/L | I65: Steady-state probability-weighted cost synergy based on the cost synergy framework.
A66: Integration Cost | B66: 0.2 | C66: 0.15 | D66: 0.1 | E66: 0.05 | F66: 0 | G66: =IF(COUNT(B66:F66)=0,"N/D",SUM(B66:F66)) -> 0.5 | H66: L | I66: Integration costs require separate analyst assumptions and should not be invented.
A67: Net Annual Synergy | B67: =IF(OR(B64="",B65="",B66=""),"N/D",B64+B65-B66) -> -0.08465 | C67: =IF(OR(C64="",C65="",C66=""),"N/D",C64+C65-C66) -> 0.0807 | D67: =IF(OR(D64="",D65="",D66=""),"N/D",D64+D65-D66) -> 0.24605 | E67: =IF(OR(E64="",E65="",E66=""),"N/D",E64+E65-E66) -> 0.4114 | F67: =IF(OR(F64="",F65="",F66=""),"N/D",F64+F65-F66) -> 0.4614 | G67: =IF(COUNT(B67:F67)=0,"N/D",SUM(B67:F67)) -> 1.1149 | H67: L/M | I67: Revenue synergy gross profit plus cost synergies less integration costs.
A68: Discount Factor | B68: =1/(1+12%)^1 -> 0.89285714 | C68: =1/(1+12%)^2 -> 0.79719388 | D68: =1/(1+12%)^3 -> 0.71178025 | E68: =1/(1+12%)^4 -> 0.63551808 | F68: =1/(1+12%)^5 -> 0.56742686 | G68: N/A | H68: Model | I68: Illustrative 12.0% discount rate. Revisit during final workbook review.
A69: Present Value of Net Synergy | B69: =IF(OR(B67="N/D",B68=""),"N/D",B67*B68) -> -0.075580357 | C69: =IF(OR(C67="N/D",C68=""),"N/D",C67*C68) -> 0.064333546 | D69: =IF(OR(D67="N/D",D68=""),"N/D",D67*D68) -> 0.17513353 | E69: =IF(OR(E67="N/D",E68=""),"N/D",E67*E68) -> 0.26145214 | F69: =IF(OR(F67="N/D",F68=""),"N/D",F67*F68) -> 0.26181075 | G69: =IF(COUNT(B69:F69)=0,"N/D",SUM(B69:F69)) -> 0.68714961 | H69: L | I69: Present value of projected net synergies using the illustrative five-year ramp and 12.0% discount rate.
A71: SYNEREGY SCORECARD
A72: Synergy/Risk | B72: Strategic Importance | C72: Financial Impact | D72: Execution Difficulty | E72: Time to Realize | F72: Evidence Quality | G72: Overall Score | H72: Confidence | I72: Conclusion
A73: Ai Coding Prooduct Acquisition | B73: 5 | C73: 5 | D73: 2 | E73: 2 | F73: 4 | G73: =IFERROR((B73+C73+(6-D73)+(6-E73)+F73)/5,"N/D") -> 4.4 | H73: M | I73: High strategic value because the transaction immediately adds an established AI coding product and developer user base.
A74: Model / Compute Cost Reduction | B74: 5 | C74: 5 | D74: 3 | E74: 3 | F74: 3 | G74: =IFERROR((B74+C74+(6-D74)+(6-E74)+F74)/5,"N/D") -> 3.8 | H74: M | I74: Potentially the largest measurable synergy, but dependent on xAI model quality and internal compute economics.
A75: Enterprise Cross Sell | B75: 4 | C75: 4 | D75: 3 | E75: 3 | F75: 3 | G75: =IFERROR((B75+C75+(6-D75)+(6-E75)+F75)/5,"N/D") -> 3.4 | H75: M/L | I75: Meaningful opportunity through SpaceX, Starlink, xAI, government, and enterprise relationships, but execution will take time.
A76: Talent Acquisition | B76: 5 | C76: 4 | D76: 3 | E76: 2 | F76: 3 | G76: =IFERROR((B76+C76+(6-D76)+(6-E76)+F76)/5,"N/D") -> 3.8 | H76: M | I76: Founders and engineering talent are strategically valuable, but retention is not guaranteed after closing.
A77: Developer Distribution | B77: 4 | C77: 4 | D77: 2 | E77: 2 | F77: 3 | G77: =IFERROR((B77+C77+(6-D77)+(6-E77)+F77)/5,"N/D") -> 3.8 | H77: M | I77: Cursor provides an established developer distribution channel that would be difficult and time-consuming to recreate internally.
A78: Model Neutrality Risk | B78: 5 | C78: 5 | D78: 4 | E78: 2 | F78: 3 | G78: =IFERROR((B78+C78+(6-D78)+(6-E78)+F78)/5,"N/D") -> 3.8 | H78: M | I78: A shift away from model neutrality could impair customer trust, product quality, and enterprise adoption.
A79: Founder/Employee Retention Risk | B79: 5 | C79: 5 | D79: 4 | E79: 2 | F79: 2 | G79: =IFERROR((B79+C79+(6-D79)+(6-E79)+F79)/5,"N/D") -> 3.6 | H79: M | I79: Founder and employee attrition could reduce the strategic value of the acquisition if retention protections are insufficient.

Sheet Regulatory Risk
A1: SPACEX ACQUISITION OF CURSOR – REGULATORY RISK
A3: Metric | B3: Description | C3: Value | D3: Units | E3: Source | F3: Confidence | G3: Status | H3: Probability | I3: Notes
A4: REGULATORY APPROVAL REQUIREMENTS
A5: Hart– Scott-Rodino Filing | B5: US premerger notification and waiting-period process expected due to transaction size, subject to exact filing exemptions and merger-agreement terms. | C5: Required / Filing Status TBD | D5: Text | E5: Merger agreement / HSR framework | F5: M | G5: Expected | I5: Confirm the exact filing date, waiting-period expiration, and any second-request disclosure from the merger filing. Do not assume clearance has occurred.
A6: FTC Review | B6: Potential review by the Federal Trade Commission depending on agency allocation and the competitive theory examined. | C6: Potential Reviewing Agency | D6: Text | E6: Merger agreement / regulatory framework | F6: M/L | G6: TBD | I6: Only one principal US antitrust agency would ordinarily lead the investigation. Confirm whether FTC or DOJ has jurisdiction before finalizing.
A7: DOJ Review | B7: Potential review by the Department of Justice depending on agency allocation and the relevant product and technology markets. | C7: Potential Reviewing Agency | D7: Text | E7: Merger agreement / regulatory framework | F7: M/L | G7: TBD | I7: Do not present both FTC and DOJ as simultaneous lead agencies. Keep both as potential until the responsible agency is confirmed.
A8: CFIUS Review | B8: Potential national-security review because SpaceX and xAI operate sensitive aerospace, defense, communications, compute, and AI assets. | C8: Potential / Assessment Required | D8: Text | E8: Merger agreement / model judgment | F8: M | G8: TBD | H8: 0.6 | I8: CFIUS jurisdiction and filing requirements depend on the transaction structure, investor ownership, sensitive data, critical technology, and foreign-person involvement. This is a risk assessment, not a confirmed filing requirement.
A9: SEC Registration Requirements | B9: Registration or disclosure requirements may apply to the issuance of SPCX Class A shares to Anysphere securityholders. | C9: Likely / Exact Form TBD | D9: Text | E9: Merger agreement / SEC filing framework | F9: M | G9: TBD | I9: Confirm whether consideration shares are registered through an SEC filing, issued through an exemption, or subject to separate registration rights.
A10: Shareholders Approval | B10: Target securityholder approval is likely required. SPCX shareholder approval depends on the merger agreement, exchange rules, share issuance size, and corporate documents. | C10: Target Required / SPCX TBD | D10: Text | E10: Merger agreement | F10: M | G10: TBD | I10: Separate target approval from acquirer approval. Do not assume SPCX shareholder approval unless specifically disclosed.
A11: Foreign Competition Reviews | B11: Additional competition, foreign investment, data, or sector approvals may apply in jurisdictions where the parties exceed filing thresholds. | C11: Potential | D11: Text | E11: Merger agreement / jurisdictional analysis | F11: M/L | G11: TBD | I11: Confirm required jurisdictions from the merger agreement. Do not list individual countries unless disclosure or threshold analysis supports them.
A13: ANTITRUST ASSESMENT
A14: Horizontal Overlap | B14: SpaceX and Cursor operate primarily in different core markets, limiting direct product overlap. | C14: Low | D14: Risk Level | E14: Model judgment | F14: M | G14: Manageable | H14: 0.85 | I14: The transaction appears more vertical and complementary than a direct horizontal consolidation, reducing conventional market-share concerns.
A15: Vertical Integration Risk | B15: Ownership could link Cursor’s developer interface and distribution with xAI foundation models, compute infrastructure, and other SpaceX-controlled assets. | C15: Medium | D15: Risk Level | E15: Model judgment | F15: M | G15: Key Review Area | H15: 0.6 | I15: Regulators could examine model self-preferencing, foreclosure of rival model providers, bundling, data access, interoperability, and reduced model neutrality.
A16: Developer Tools Market Share | B16: Cursor is a significant AI coding product, but an exact defensible market share is not available in the current workbook. | C16: N/D | D16: % | E16: Company / market research required | F16: L | G16: Open Diligence Item | I16: Do not insert an unsupported market-share percentage. Define the relevant market before calculating share.
A17: AI Foundation Model Market Share | B17: xAI’s exact share of the AI foundation-model market is not established in the current workbook. | C17: N/D | D17: % | E17: Market research required | F17: L | G17: Open Diligence Item | I17: Competitive significance may be greater in coding-specific models than in the broader foundation-model market.
A18: Cloud Infrastructure Concentration | B18: The transaction may increase dependence on vertically integrated model and compute infrastructure, but SpaceX is not presented as the dominant public cloud provider. | C18: Medium | D18: Risk Level | E18: Model judgment | F18: M/L | G18: Monitor | H18: 0.5 | I18: The primary concern is not conventional public-cloud concentration but potential integration of compute, models, developer distribution, and customer data.
A19: Antitrust Risk Score | B19: Overall antitrust risk based on limited horizontal overlap but meaningful vertical-integration and model-neutrality questions. | C19: 2.5 | D19: 1–5 Score | E19: Model judgment | F19: M | G19: Low / Moderate | H19: 0.8 | I19: A score of 1 indicates minimal risk and 5 indicates severe risk. Current preliminary score assumes no evidence of dominant market shares or explicit foreclosure conduct.
A21: NATIONAL SECURITY REVIEW
A22: Sensitive Technologies | B22: The combined company would control advanced AI coding technology, source-code workflows, model access, compute resources, communications infrastructure, and potentially sensitive technical data. | C22: High | D22: Risk Level | E22: Model judgment | F22: M | G22: Material Review Area | H22: 0.75 | I22: The sensitivity of source code, model infrastructure, aerospace technology, and government-related data increases review relevance.
A23: Government Customers | B23: SpaceX maintains significant government, civil-space, national-security, defense, and communications relationships. | C23: High | D23: Exposure Level | E23: SPCX filings / company materials | F23: H/M | G23: Relevant | H23: 0.9 | I23: Government customer exposure does not itself block the deal but increases scrutiny around data separation, cybersecurity, access controls, and continuity.
A24: Defense Applications | B24: Cursor technology could support software development for aerospace, defense, cybersecurity, communications, and other sensitive applications. | C24: Medium / High | D24: Risk Level | E24: Model judgment | F24: M | G24: Relevant | H24: 0.7 | I24: Risk depends on customer usage, deployment architecture, source-code access, model training practices, and government-contract restrictions.
A25: Foreign Ownership Concerns | B25: The current workbook does not establish material foreign ownership or control concerns in Anysphere or the consideration structure. | C25: TBD | D25: Text | E25: PitchBook / merger filing required | F25: L/M | G25: Open Diligence Item | I25: Review Anysphere’s cap table, investor rights, board rights, beneficial ownership, and any foreign-government or foreign-person interests before concluding.
A26: CFIUS Probability | B26: Preliminary probability that the transaction receives meaningful CFIUS or national-security assessment. | C26: 0.6 | D26: % | E26: Model judgment | F26: M/L | G26: Moderate | H26: 0.6 | I26: This is an assessment probability, not a confirmed filing probability. Update after reviewing the merger agreement and ownership disclosures.
A27: National Security Risk Score | B27: Overall national-security risk based on technology sensitivity, government exposure, data access, and unresolved ownership questions. | C27: 3 | D27: 1–5 Score | E27: Model judgment | F27: M | G27: Moderate | H27: 0.7 | I27: A score of 1 indicates minimal risk and 5 indicates severe risk. Current score reflects likely scrutiny but not a base-case block.
A29: CLOSING RISK ANALYSIS
A30: Base Closing Probability | B30: Preliminary probability of closing before deducting the modeled block and financing risks below. | C30: 0.9 | D30: % | E30: Model judgment | F30: M | G30: Base Case | H30: 0.9 | I30: Reflects strategic commitment, all-stock consideration, and the stated Q3 2026 closing target, subject to regulatory and transaction-specific conditions.
A31: Regulatory Delay Probability | B31: Probability that regulatory review delays closing beyond the initially expected Q3 2026 period without permanently blocking the deal. | C31: 0.35 | D31: % | E31: Model judgment | F31: M/L | G31: Moderate | H31: 0.35 | I31: A delay can occur even if the transaction ultimately closes. Do not subtract delay probability directly from the eventual closing probability.
A32: Regulatory Block Probability | B32: Probability that regulatory action, litigation, or an inability to satisfy approval conditions permanently prevents closing. | C32: 0.1 | D32: % | E32: Model judgment | F32: M/L | G32: Low | H32: 0.1 | I32: Preliminary block probability reflects limited horizontal overlap but unresolved vertical, data, national-security, and model-neutrality issues.
A33: Financing Risk | B33: Risk that SpaceX cannot fund or issue the required stock consideration or satisfy transaction-related financial conditions. | C33: 0.02 | D33: % | E33: Model judgment | F33: M | G33: Low | H33: 0.02 | I33: All-stock consideration materially reduces conventional debt-financing risk, although closing conditions and share-issuance mechanics still matter.
A34: Share Price Risk | B34: Risk that SPCX share-price volatility changes dilution and share issuance before closing. | C34: 0.4 | D34: % | E34: Model judgment | F34: M | G34: Economic Risk | H34: 0.4 | I34: The floating value exchange ratio protects Cursor sellers’ dollar consideration but exposes SPCX shareholders to greater dilution if the stock declines. This is primarily an economic risk rather than a financing failure risk.
A35: Overall Closing Probability | B35: Probability-weighted closing estimate after applying modeled regulatory block and financing risk to the base closing probability. | C35: =MAX(0,C30*(1-C32)*(1-C33)) -> 0.7938 | D35: % | E35: Formula | F35: M | G35: High Probability | H35: =C35 -> 0.7938 | I35: Regulatory delay probability and share-price volatility are not deducted because they may affect timing or economics without preventing eventual closing.
A37: BREAK SCENERIO ECONOMICS
A38: Breakup fee | B38: Reported cash breakup-fee component payable under the April option or walk-away arrangement. | C38: ='Deal Fact Sheet '!C20 -> 1.5 | D38: $B | E38: Deal Fact Sheet / press | F38: M | G38: Reported | I38: Confirm whether the $1.5B amount is a formal merger termination fee, option fee, or another contractual payment.
A39: Compute Commitment | B39: Reported compute commitment included in the broader walk-away economics. | C39: ='Deal Fact Sheet '!C21 -> 8.5 | D39: $B | E39: Deal Fact Sheet / press | F39: M/L | G39: Reported | I39: Compute consideration may differ economically from cash because its value depends on capacity, pricing, timing, and utilization.
A40: Total Break Cost | B40: Total reported walk-away economics. | C40: =SUM(C38:C39) -> 10 | D40: $B | E40: Formula | F40: M | G40: Calculated | I40: Equals the reported breakup-fee component plus the reported compute commitment.
A41: Break Cost as % of Deal Value | B41: Total reported break cost as a percentage of the $60.0B transaction value. | C41: =IFERROR(C40/'Deal Fact Sheet '!C13,"N/D") -> 0.16666667 | D41: % | E41: Formula | F41: M | G41: Calculated | I41: A 16.7% break cost would be unusually large relative to standard public-company termination fees, so contractual characterization must be verified carefully.
A42: Cursor Standalone Value | B42: Preliminary standalone fair-value estimate if the transaction does not close. | C42: ='Cursor Valuation '!D43 -> 50 | D42: $B | E42: Cursor Valuation | F42: M | G42: Model Estimate | I42: Uses the base-case implied value from the Cursor Valuation fair-value framework. This is not a market-observed standalone value.
A43: Value Lost If Deal Breaks | B43: Difference between the transaction price and the preliminary standalone fair-value estimate. | C43: =MAX(0,'Deal Fact Sheet '!C13-C42) -> 10 | D43: $B | E43: Formula | F43: M | G43: Calculated | I43: Represents value at risk to Cursor sellers relative to the transaction price if the deal breaks and Cursor reverts to the modeled standalone base case.
A45: REGULATORY CONCLUSIONS
A46: Antitrust Block Risk | B46: Risk that competition authorities permanently prohibit the transaction. | C46: Low / Moderate | D46: Risk Level | E46: Model judgment | F46: M | G46: Manageable | H46: =C32 -> 0.1 | I46: Limited direct horizontal overlap reduces block risk, but vertical integration, model access, data, bundling, and foreclosure theories could extend review.
A47: National Security Review Risk | B47: Risk that national-security review delays the transaction or results in mitigation conditions. | C47: Moderate | D47: Risk Level | E47: Model judgment | F47: M | G47: Key Review Area | H47: =C26 -> 0.6 | I47: Sensitive technology, government relationships, source-code access, and ownership diligence could lead to mitigation requirements even if the deal is ultimately approved.
A48: Expected Review Duration | B48: Preliminary expected review and closing period. | C48: Q3 2026 Target; Delay Possible | D48: Text | E48: Merger filing / model judgment | F48: M | G48: Monitor | H48: =C31 -> 0.35 | I48: The disclosed Q3 2026 target may remain achievable, but a detailed second request, national-security mitigation process, or foreign review could extend closing.
A49: Most Likely Outcome | B49: Most probable transaction outcome based on the current preliminary risk assessment. | C49: Approved, Potentially with Conditions | D49: Text | E49: Model judgment | F49: M | G49: Base Case | H49: =C35 -> 0.7938 | I49: The base case is eventual approval because the acquisition appears strategically complementary, but conditions may address data access, security, interoperability, model neutrality, or government-related controls.
A50: Overall Regulatory Verdict | B50: Overall regulatory assessment. | C50: Moderate Execution Risk / High Closing Probability | D50: Text | E50: Model judgment | F50: M | G50: Proceed with Monitoring | H50: =C35 -> 0.7938 | I50: Regulatory risk is meaningful but does not currently appear sufficient to make deal failure the base case. The largest unresolved issues are vertical integration, sensitive data, national security, foreign ownership, and the exact approval conditions in the merger agreement.

Sheet PB_CACHE_JS
A1: {"Deal Fact Sheet ":{"MATCHPBID|^SpaceX ":{"r":[["46488-07"]]},"MATCHPBID|^spcx":{"r":[["46488-07"]]},"MATCHPBID|^Anysphere":{"r":[["519419-89"]]},"MATCHPBID|^Cursor":{"r":[["519419-89"]]},"MATCHPBID|^SPCX":{"r":[["46488-07"]]},"MATCHPBID|^Announced/ Pending Close":{"r":[["#NOMATCH"]]},"MATCHPBID|^Floating Value/ VWAP– Set Ratio":{"r":[["#NOMATCH"]]},"MATCHPBID|^60":{"r":[["233709-40"]]},"MATCHPBID|^All Stock ":{"r":[["169307-83"]]},"MATCHPBID|^Q3 2026":{"r":[["#NOMATCH"]]},"MATCHPBID|^46133":{"r":[["#NOMATCH"]]},"MATCHPBID|^10":{"r":[["60318-10"]]},"MATCHPBID|^SPCX Class A Shares ":{"r":[["#NOMATCH"]]},"MATCHPBID|^Non–Disclosed/TBD":{"r":[["#NOMATCH"]]},"MATCHPBID|^1.5":{"r":[["519212-80"]]},"MATCHPBID|^8.5":{"r":[["150705-10"]]},"MATCHPBID|^7 Trading days Before the Close ":{"r":[["#NOMATCH"]]},"MATCHPBID|^TBD per Filing":{"r":[["#NOMATCH"]]},"D|^287345-62TDeal DateUSD":{"r":[[45813]],"a":["'Deal Fact Sheet '!C38"],"c":[["dd-mmm-yy"]]},"D|^287345-62TDeal AmountUSD":{"r":[[899998983]],"a":["'Deal Fact Sheet '!C39"]},"D|^/1000000000287345-62TDeal AmountUSD":{"r":[[0.899998983]],"a":["'Deal Fact Sheet '!C39"]},"D|^/1000000287345-62TDeal AmountUSD":{"r":[[899.998983]],"a":["'Deal Fact Sheet '!C39"]},"D|^/1000000287345-62TDeal Post ValuationUSD":{"r":[[9900.000048]],"a":["'Deal Fact Sheet '!C40"]},"D|^/1000000000287345-62TDeal Post ValuationUSD":{"r":[[9.900000048]],"a":["'Deal Fact Sheet '!C40"]},"D|^/1000000000identifierDeal DateUSD":{"id":47,"description":null,"headerValues":[],"financialValues":[],"customValues":[],"error":"PBXLP_ENTITY_ID"},"D|^/1000000000312975-01TDeal DateUSD":{"r":[[45974]],"c":[["dd-mmm-yy"]],"a":["'Deal Fact Sheet '!C41","'Deal Fact Sheet '!C42"]},"D|^/1000000000312975-01TDeal AmountUSD":{"r":[[2.300000297]],"a":["'Deal Fact Sheet '!C42"]},"D|^/10000000287345-62TDeal AmountUSD":{"r":[[89.9998983]],"a":["'Deal Fact Sheet '!C39"]},"D|^/1000000000312975-01TDeal Post ValuationUSD":{"r":[[29.300000333]],"a":["'Deal Fact Sheet '!C43"]},"D|^/1000000000519419-89Last Known Valuation Deal TypeUSD":{"r":[["Later Stage VC"]],"a":["'Deal Fact Sheet '!C44"]},"M|^46488-07Close Price06/16/202606/16/2026dasc0USD":{"r":[[201.8]],"c":[[]],"a":["'Deal Fact Sheet '!B69","'Deal Fact Sheet '!C69","'Deal Fact Sheet '!C70"]},"M|^46488-07Close Price06/15/202606/15/2026dasc0USD":{"r":[[192.5]],"c":[[]],"a":["'Deal Fact Sheet '!B69","'Deal Fact Sheet '!C70"]},"M|^519419-89Close Price06/16/202606/16/2026dasc0USD":{"id":7,"description":null,"headerValues":[],"financialValues":[],"customValues":[],"error":null},"M|^/100000000046488-07Market Cap06/16/202606/16/2026dasc0USD":{"r":[[2658.550996736]],"c":[[]],"a":["'Deal Fact Sheet '!C71"]},"D|^/1000000000519419-89Most Recent Post ValuationUSD":{"r":[[60]],"a":["'Deal Fact Sheet '!C72"]}},"Comps ":{"MATCHPBID|^GitLab":{"r":[["84804-13"]]},"MATCHPBID|^Atlassian":{"r":[["45245-62"]]},"MATCHPBID|^Datadog":{"r":[["53904-79"]]},"MATCHPBID|^Snowflake":{"r":[["61489-18"]]},"MATCHPBID|^Confluent":{"r":[["99264-61"]]},"MATCHPBID|^HashiCorp":{"r":[["59113-45"]]},"MATCHPBID|^Elastic":{"r":[["55574-02"]]},"MATCHPBID|^GitHub":{"r":[["54525-52"]]},"MATCHPBID|^MongoDB":{"r":[["51351-85"]]},"MATCHPBID|^Cloudflare":{"r":[["52368-49"]]},"MATCHSYMBOL|^GitLab":{"r":[["NAS:GTLB"]]},"MATCHSYMBOL|^Snowflake":{"r":[["NYS:SNOW"]]},"MATCHSYMBOL|^MongoDB":{"r":[["NAS:MDB"]]},"MATCHSYMBOL|^Elastic":{"r":[["NYS:ESTC"]]},"MATCHSYMBOL|^GitHub":{"r":[["#NOMATCH"]]},"MATCHSYMBOL|^Atlassian":{"r":[["NAS:TEAM"]]},"MATCHSYMBOL|^HashiCorp":{"r":[["#NOMATCH"]]},"MATCHSYMBOL|^Datadog":{"r":[["NAS:DDOG"]]},"MATCHSYMBOL|^Cloudflare":{"r":[["NYS:NET"]]},"MATCHSYMBOL|^Confluent":{"r":[["#NOMATCH"]]},"MATCHSYMBOL|^99264-61":{"r":[["#NOMATCH"]]},"M|^/100000000084804-13Market Cap07/12/202607/12/2026dasc0USD":{"r":[[5.475738]],"c":[[]],"a":["'Comps '!D5"]},"M|^/100000000061489-18Market Cap07/12/202607/12/2026dasc0USD":{"r":[[90.61857]],"c":[[]],"a":["'Comps '!D10"]},"M|^/100000000055574-02Market Cap07/12/202607/12/2026dasc0USD":{"r":[[6.262046372]],"c":[[]],"a":["'Comps '!D11"]},"M|^/100000000045245-62Market Cap07/12/202607/12/2026dasc0USD":{"r":[[22.549812218]],"c":[[]],"a":["'Comps '!D6"]},"M|^/100000000053904-79Market Cap07/12/202607/12/2026dasc0USD":{"r":[[91.673987075]],"c":[[]],"a":["'Comps '!D7"]},"M|^/100000000052368-49Market Cap07/12/202607/12/2026dasc0USD":{"r":[[95.265778978]],"c":[[]],"a":["'Comps '!D8"]},"M|^/100000000051351-85Market Cap07/12/202607/12/2026dasc0USD":{"r":[[27.514153588]],"c":[[]],"a":["'Comps '!D9"]},"M|^/100000000059113-45Market Cap07/12/202607/12/2026dasc0USD":{"id":50,"description":null,"headerValues":[],"financialValues":[],"customValues":[],"error":null},"M|^/100000000099264-61Market Cap07/12/202607/12/2026dasc0USD":{"id":45,"description":null,"headerValues":[],"financialValues":[],"customValues":[],"error":null},"M|^/100000000054525-52Market Cap07/12/202607/12/2026dasc0USD":{"id":47,"description":null,"headerValues":[],"financialValues":[],"customValues":[],"error":null},"F|^84804-13EVNTM07/12/2026USD":{"r":[[4164455000]],"c":null,"a":["'Comps '!E5"]},"F|^53904-79EVNTM07/12/2026USD":{"r":[[88200422075]],"c":null,"a":["'Comps '!E7"]},"F|^54525-52EVNTM07/12/2026USD":{"id":59,"description":null,"headerValues":[],"financialValues":[],"customValues":[],"error":null},"F|^52368-49EVNTM07/12/2026USD":{"r":[[94626436978]],"c":null,"a":["'Comps '!E8"]},"F|^55574-02EVNTM07/12/2026USD":{"r":[[5483347372]],"c":null,"a":["'Comps '!E11"]},"F|^45245-62EVNTM07/12/2026USD":{"r":[[22656488218]],"c":null,"a":["'Comps '!E6"]},"F|^51351-85EVNTM07/12/2026USD":{"r":[[25117427588]],"c":null,"a":["'Comps '!E9"]},"F|^61489-18EVNTM07/12/2026USD":{"r":[[90435667000]],"c":null,"a":["'Comps '!E10"]},"F|^99264-61EVNTM07/12/2026USD":{"id":57,"description":null,"headerValues":[],"financialValues":[],"customValues":[],"error":null},"F|^59113-45EVNTM07/12/2026USD":{"id":58,"description":null,"headerValues":[],"financialValues":[],"customValues":[],"error":null},"F|^84804-13Total RevenueNTM07/12/2026USD":{"r":[[1004873000]],"c":null,"a":["'Comps '!F5"]},"F|^53904-79Total RevenueNTM07/12/2026USD":{"r":[[3672031000]],"c":null,"a":["'Comps '!F7"]},"F|^54525-52Total RevenueNTM07/12/2026USD":{"id":67,"description":null,"headerValues":[],"financialValues":[],"customValues":[],"error":null},"F|^59113-45Total RevenueNTM07/12/2026USD":{"id":69,"description":null,"headerValues":[],"financialValues":[],"customValues":[],"error":null},"F|^52368-49Total RevenueNTM07/12/2026USD":{"r":[[2328605000]],"c":null,"a":["'Comps '!F8"]},"F|^55574-02Total RevenueNTM07/12/2026USD":{"r":[[1739331000]],"c":null,"a":["'Comps '!F11"]},"F|^45245-62Total RevenueNTM07/12/2026USD":{"r":[[6190183000]],"c":null,"a":["'Comps '!F6"]},"F|^51351-85Total RevenueNTM07/12/2026USD":{"r":[[2602399000]],"c":null,"a":["'Comps '!F9"]},"F|^61489-18Total RevenueNTM07/12/2026USD":{"r":[[5032823000]],"c":null,"a":["'Comps '!F10"]},"F|^99264-61Total RevenueNTM07/12/2026USD":{"r":[[1166748000]],"c":null,"a":["'Comps '!F12"]},"D|^84804-13Revenue % GrowthUSD":{"id":71,"description":null,"headerValues":[{"simpleDate":null,"value":"PBXLP_WRONG_INPUT","description":null}],"financialValues":[],"customValues":[],"error":null},"F|^84804-13Revenue % GrowthNTM07/12/2026USD":{"r":[[0.24895503317917256]],"c":null,"a":["'Comps '!G5"]},"F|^53904-79Revenue % GrowthNTM07/12/2026USD":{"r":[[0.29544323223058133]],"c":null,"a":["'Comps '!G7"]},"F|^54525-52Revenue % GrowthNTM07/12/2026USD":{"id":8,"description":null,"headerValues":[],"financialValues":[],"customValues":[],"error":null},"F|^59113-45Revenue % GrowthNTM07/12/2026USD":{"id":10,"description":null,"headerValues":[],"financialValues":[],"customValues":[],"error":null},"F|^52368-49Revenue % GrowthNTM07/12/2026USD":{"r":[[0.3155135468905623]],"c":null,"a":["'Comps '!G8"]},"F|^55574-02Revenue % GrowthNTM07/12/2026USD":{"r":[[0.17261220956572387]],"c":null,"a":["'Comps '!G11"]},"F|^45245-62Revenue % GrowthNTM07/12/2026USD":{"r":[[0.24737947224713097]],"c":null,"a":["'Comps '!G6"]},"F|^51351-85Revenue % GrowthNTM07/12/2026USD":{"r":[[0.23635514533734692]],"c":null,"a":["'Comps '!G9"]},"F|^61489-18Revenue % GrowthNTM07/12/2026USD":{"r":[[0.3107125677874223]],"c":null,"a":["'Comps '!G10"]},"F|^99264-61Revenue % GrowthNTM07/12/2026USD":{"r":[[0.2107691445578337]],"c":null,"a":["'Comps '!G12"]},"F|^84804-13EV to RevenueNTM07/12/2026USD":{"r":[[4.1442600209180664]],"c":null,"a":["'Comps '!H5"]},"F|^53904-79EV to RevenueNTM07/12/2026USD":{"r":[[24.019520008137185]],"c":null,"a":["'Comps '!H7"]},"F|^54525-52EV to RevenueNTM07/12/2026USD":{"id":15,"description":null,"headerValues":[],"financialValues":[],"customValues":[],"error":null},"F|^52368-49EV to RevenueNTM07/12/2026USD":{"r":[[40.63653431045626]],"c":null,"a":["'Comps '!H8"]},"F|^55574-02EV to RevenueNTM07/12/2026USD":{"r":[[3.1525611697830946]],"c":null,"a":["'Comps '!H11"]},"F|^45245-62EV to RevenueNTM07/12/2026USD":{"r":[[3.6600675970322687]],"c":null,"a":["'Comps '!H6"]},"F|^51351-85EV to RevenueNTM07/12/2026USD":{"r":[[9.65164357502443]],"c":null,"a":["'Comps '!H9"]},"F|^61489-18EV to RevenueNTM07/12/2026USD":{"r":[[17.96917296713991]],"c":null,"a":["'Comps '!H10"]},"F|^59113-45EV to RevenueNTM07/12/2026USD":{"id":16,"description":null,"headerValues":[],"financialValues":[],"customValues":[],"error":null},"F|^99264-61EV to RevenueNTM07/12/2026USD":{"id":18,"description":null,"headerValues":[],"financialValues":[],"customValues":[],"error":null},"F|^84804-13EBITDA MarginNTM07/12/2026USD":{"r":[[-0.052350894093084396]],"c":null,"a":["'Comps '!I5"]},"F|^53904-79EBITDA MarginNTM07/12/2026USD":{"r":[[0.009705800413994325]],"c":null,"a":["'Comps '!I7"]},"F|^54525-52EBITDA MarginNTM07/12/2026USD":{"id":29,"description":null,"headerValues":[],"financialValues":[],"customValues":[],"error":null},"F|^59113-45EBITDA MarginNTM07/12/2026USD":{"id":31,"description":null,"headerValues":[],"financialValues":[],"customValues":[],"error":null},"F|^52368-49EBITDA MarginNTM07/12/2026USD":{"r":[[-0.005195814661567762]],"c":null,"a":["'Comps '!I8"]},"F|^55574-02EBITDA MarginNTM07/12/2026USD":{"r":[[0.01993582590087798]],"c":null,"a":["'Comps '!I11"]},"F|^45245-62EBITDA MarginNTM07/12/2026USD":{"r":[[-0.018099949549149032]],"c":null,"a":["'Comps '!I6"]},"F|^51351-85EBITDA MarginNTM07/12/2026USD":{"r":[[-0.022158400767906844]],"c":null,"a":["'Comps '!I9"]},"F|^61489-18EBITDA MarginNTM07/12/2026USD":{"r":[[-0.22161200582655102]],"c":null,"a":["'Comps '!I10"]},"F|^99264-61EBITDA MarginNTM07/12/2026USD":{"r":[[-0.2323826567519293]],"c":null,"a":["'Comps '!I12"]},"M|^/100000000084804-13Market Cap06/16/202606/16/2026dasc0USD":{"r":[[4.697109]],"c":[[]],"a":["'Comps '!D5"]},"M|^/100000000051351-85Market Cap06/16/202606/16/2026dasc0USD":{"r":[[28.055460457]],"c":[[]],"a":["'Comps '!D9"]},"M|^/100000000052368-49Market Cap06/16/202606/16/2026dasc0USD":{"r":[[81.980391097]],"c":[[]],"a":["'Comps '!D8"]},"M|^/100000000061489-18Market Cap06/16/202606/16/2026dasc0USD":{"r":[[82.601712]],"c":[[]],"a":["'Comps '!D10"]},"M|^/100000000053904-79Market Cap06/16/202606/16/2026dasc0USD":{"r":[[82.26595928]],"c":[[]],"a":["'Comps '!D7"]},"M|^/100000000045245-62Market Cap06/16/202606/16/2026dasc0USD":{"r":[[22.318883463]],"c":[[]],"a":["'Comps '!D6"]},"M|^/100000000055574-02Market Cap06/16/202606/16/2026dasc0USD":{"r":[[6.24853266]],"c":[[]],"a":["'Comps '!D11"]},"M|^/100000000099264-61Market Cap06/16/202606/16/2026dasc0USD":{"id":36,"description":null,"headerValues":[],"financialValues":[],"customValues":[],"error":null},"M|^/100000000054525-52Market Cap06/16/202606/16/2026dasc0USD":{"id":39,"description":null,"headerValues":[],"financialValues":[],"customValues":[],"error":null},"M|^/100000000059113-45Market Cap06/16/202606/16/2026dasc0USD":{"id":40,"description":null,"headerValues":[],"financialValues":[],"customValues":[],"error":null},"F|^84804-13EVNTM06/16/2026USD":{"r":[[3385826000]],"c":null,"a":["'Comps '!E5"]},"F|^53904-79EVNTM06/16/2026USD":{"r":[[78792394280]],"c":null,"a":["'Comps '!E7"]},"F|^54525-52EVNTM06/16/2026USD":{"id":48,"description":null,"headerValues":[],"financialValues":[],"customValues":[],"error":null},"F|^52368-49EVNTM06/16/2026USD":{"r":[[81341049097]],"c":null,"a":["'Comps '!E8"]},"F|^55574-02EVNTM06/16/2026USD":{"r":[[5469833660]],"c":null,"a":["'Comps '!E11"]},"F|^45245-62EVNTM06/16/2026USD":{"r":[[22425559463]],"c":null,"a":["'Comps '!E6"]},"F|^51351-85EVNTM06/16/2026USD":{"r":[[25658734457]],"c":null,"a":["'Comps '!E9"]},"F|^61489-18EVNTM06/16/2026USD":{"r":[[82418809000]],"c":null,"a":["'Comps '!E10"]},"F|^59113-45EVNTM06/16/2026USD":{"id":49,"description":null,"headerValues":[],"financialValues":[],"customValues":[],"error":null},"F|^99264-61EVNTM06/16/2026USD":{"id":47,"description":null,"headerValues":[],"financialValues":[],"customValues":[],"error":null},"F|^84804-13Total RevenueNTM06/16/2026USD":{"r":[[1004873000]],"c":null,"a":["'Comps '!F5"]},"F|^53904-79Total RevenueNTM06/16/2026USD":{"r":[[3672031000]],"c":null,"a":["'Comps '!F7"]},"F|^54525-52Total RevenueNTM06/16/2026USD":{"id":58,"description":null,"headerValues":[],"financialValues":[],"customValues":[],"error":null},"F|^59113-45Total RevenueNTM06/16/2026USD":{"id":62,"description":null,"headerValues":[],"financialValues":[],"customValues":[],"error":null},"F|^52368-49Total RevenueNTM06/16/2026USD":{"r":[[2328605000]],"c":null,"a":["'Comps '!F8"]},"F|^55574-02Total RevenueNTM06/16/2026USD":{"r":[[1739331000]],"c":null,"a":["'Comps '!F11"]},"F|^45245-62Total RevenueNTM06/16/2026USD":{"r":[[6190183000]],"c":null,"a":["'Comps '!F6"]},"F|^51351-85Total RevenueNTM06/16/2026USD":{"r":[[2602399000]],"c":null,"a":["'Comps '!F9"]},"F|^61489-18Total RevenueNTM06/16/2026USD":{"r":[[5032823000]],"c":null,"a":["'Comps '!F10"]},"F|^99264-61Total RevenueNTM06/16/2026USD":{"r":[[1166748000]],"c":null,"a":["'Comps '!F12"]},"F|^84804-13Revenue % GrowthNTM06/16/2026USD":{"r":[[0.24895503317917256]],"c":null,"a":["'Comps '!G5"]},"F|^53904-79Revenue % GrowthNTM06/16/2026USD":{"r":[[0.29544323223058133]],"c":null,"a":["'Comps '!G7"]},"F|^54525-52Revenue % GrowthNTM06/16/2026USD":{"id":69,"description":null,"headerValues":[],"financialValues":[],"customValues":[],"error":null},"F|^59113-45Revenue % GrowthNTM06/16/2026USD":{"id":71,"description":null,"headerValues":[],"financialValues":[],"customValues":[],"error":null},"F|^52368-49Revenue % GrowthNTM06/16/2026USD":{"r":[[0.3155135468905623]],"c":null,"a":["'Comps '!G8"]},"F|^55574-02Revenue % GrowthNTM06/16/2026USD":{"r":[[0.17261220956572387]],"c":null,"a":["'Comps '!G11"]},"F|^45245-62Revenue % GrowthNTM06/16/2026USD":{"r":[[0.24737947224713097]],"c":null,"a":["'Comps '!G6"]},"F|^51351-85Revenue % GrowthNTM06/16/2026USD":{"r":[[0.23635514533734692]],"c":null,"a":["'Comps '!G9"]},"F|^61489-18Revenue % GrowthNTM06/16/2026USD":{"r":[[0.3107125677874223]],"c":null,"a":["'Comps '!G10"]},"F|^99264-61Revenue % GrowthNTM06/16/2026USD":{"r":[[0.2107691445578337]],"c":null,"a":["'Comps '!G12"]},"F|^84804-13EV to RevenueNTM06/16/2026USD":{"r":[[3.3694068802724324]],"c":null,"a":["'Comps '!H5"]},"F|^53904-79EV to RevenueNTM06/16/2026USD":{"r":[[21.45744256516353]],"c":null,"a":["'Comps '!H7"]},"F|^54525-52EV to RevenueNTM06/16/2026USD":{"id":80,"description":null,"headerValues":[],"financialValues":[],"customValues":[],"error":null},"F|^52368-49EV to RevenueNTM06/16/2026USD":{"r":[[34.931235266178675]],"c":null,"a":["'Comps '!H8"]},"F|^55574-02EV to RevenueNTM06/16/2026USD":{"r":[[3.144791681399343]],"c":null,"a":["'Comps '!H11"]},"F|^45245-62EV to RevenueNTM06/16/2026USD":{"r":[[3.6227619543719465]],"c":null,"a":["'Comps '!H6"]},"F|^51351-85EV to RevenueNTM06/16/2026USD":{"r":[[9.859646601846988]],"c":null,"a":["'Comps '!H9"]},"F|^61489-18EV to RevenueNTM06/16/2026USD":{"r":[[16.376258215319712]],"c":null,"a":["'Comps '!H10"]},"F|^99264-61EV to RevenueNTM06/16/2026USD":{"id":84,"description":null,"headerValues":[],"financialValues":[],"customValues":[],"error":null},"F|^59113-45EV to RevenueNTM06/16/2026USD":{"id":85,"description":null,"headerValues":[],"financialValues":[],"customValues":[],"error":null},"F|^84804-13EBITDA MarginNTM06/16/2026USD":{"r":[[-0.052350894093084396]],"c":null,"a":["'Comps '!I5"]},"F|^53904-79EBITDA MarginNTM06/16/2026USD":{"r":[[0.009705800413994325]],"c":null,"a":["'Comps '!I7"]},"F|^54525-52EBITDA MarginNTM06/16/2026USD":{"id":93,"description":null,"headerValues":[],"financialValues":[],"customValues":[],"error":null},"F|^59113-45EBITDA MarginNTM06/16/2026USD":{"id":91,"description":null,"headerValues":[],"financialValues":[],"customValues":[],"error":null},"F|^52368-49EBITDA MarginNTM06/16/2026USD":{"r":[[-0.005195814661567762]],"c":null,"a":["'Comps '!I8"]},"F|^55574-02EBITDA MarginNTM06/16/2026USD":{"r":[[0.01993582590087798]],"c":null,"a":["'Comps '!I11"]},"F|^45245-62EBITDA MarginNTM06/16/2026USD":{"r":[[-0.018099949549149032]],"c":null,"a":["'Comps '!I6"]},"F|^51351-85EBITDA MarginNTM06/16/2026USD":{"r":[[-0.022158400767906844]],"c":null,"a":["'Comps '!I9"]},"F|^61489-18EBITDA MarginNTM06/16/2026USD":{"r":[[-0.22161200582655102]],"c":null,"a":["'Comps '!I10"]},"F|^99264-61EBITDA MarginNTM06/16/2026USD":{"r":[[-0.2323826567519293]],"c":null,"a":["'Comps '!I12"]}},"Dilution Market":{"M|^/100000000046488-07Market Cap06/16/202606/16/2026dasc0USD":{"r":[[2658.550996736]],"c":[[]],"a":["'Dilution Market'!C6","'Dilution Market'!C13","'Dilution Market'!C16"]},"M|^/100000000046488-07Market Capdasc0USD":{"r":[[1914.209414399]],"c":[[]],"a":["'Dilution Market'!C6"]},"M|^/100000000046488-07Market Cap06/15/202606/16/2026dasc0USD":{"r":[[2536.031054865],[2658.550996736]],"c":[[]],"a":["'Dilution Market'!C6"]},"M|^/100000000046488-07Market Cap06/15/202606/15/2026dasc0USD":{"r":[[2536.031054865]],"c":[[]],"a":["'Dilution Market'!C6","'Dilution Market'!C12","'Dilution Market'!C15"]},"MATCHPBID|^SPCX":{"r":[["46488-07"]]},"MATCHPBID|^Anysphere":{"r":[["519419-89"]]},"MATCHPBID|^Cursor":{"r":[["519419-89"]]},"MATCHPBID|^Announced / Pending Close":{"r":[["#NOMATCH"]]},"MATCHPBID|^All Stock ":{"r":[["169307-83"]]},"MATCHPBID|^SPCX Class A Shares ":{"r":[["#NOMATCH"]]},"MATCHPBID|^Floating Value/ VWAP– Set Ratio":{"r":[["#NOMATCH"]]},"MATCHPBID|^60":{"r":[["233709-40"]]},"M|^46488-07Close Price06/15/202606/15/2026dasc0USD":{"r":[[192.5]],"c":[[]],"a":["'Dilution Market'!C12"]},"M|^46488-07Close Price06/16/202606/16/2026dasc0USD":{"r":[[201.8]],"c":[[]],"a":["'Dilution Market'!C13"]}}}

Sheet CACHE_CHARTS_JS
